Workbook

Sheet 2025
A1: Rank | B1: Country | C1: Price To Income Ratio | D1: Gross Rental Yield City Centre | E1: Gross Rental Yield Outside of Centre | F1: Price To Rent Ratio City Centre | G1: Price To Rent Ratio Outside Of City Centre | H1: Mortgage As A Percentage Of Income | I1: Affordability Index
A2: 1 | B2: Syria | C2: 115.1 | D2: 2.4 | E2: 3.8 | F2: 41.1 | G2: 26.3 | H2: 1746.8 | I2: 0.1
A3: 2 | B3: Cuba | C3: 48 | D3: 24 | E3: 28.3 | F3: 4.2 | G3: 3.5 | H3: 530.3 | I3: 0.2
A4: 3 | B4: Ethiopia | C4: 47.1 | D4: 6 | E4: 5.4 | F4: 16.7 | G4: 18.6 | H4: 762.3 | I4: 0.1
A5: 4 | B5: Cameroon | C5: 46.6 | D5: 9.2 | E5: 11.4 | F5: 10.8 | G5: 8.8 | H5: 907.8 | I5: 0.1
A6: 5 | B6: Sri Lanka | C6: 34.2 | D6: 3.7 | E6: 2.7 | F6: 26.7 | G6: 36.5 | H6: 603.5 | I6: 0.2
A7: 6 | B7: Nepal | C7: 32.1 | D7: 1.7 | E7: 1.8 | F7: 60 | G7: 56.3 | H7: 447.4 | I7: 0.2
A8: 7 | B8: Hong Kong (China) | C8: 29.1 | D8: 1.9 | E8: 2.2 | F8: 52.2 | G8: 44.7 | H8: 211.2 | I8: 0.5
A9: 8 | B9: China | C9: 28.5 | D9: 1.6 | E9: 1.9 | F9: 62.5 | G9: 51.8 | H9: 212.9 | I9: 0.5
A10: 9 | B10: Vietnam | C10: 25.8 | D10: 3 | E10: 3.6 | F10: 33.3 | G10: 28 | H10: 296.2 | I10: 0.3
A11: 10 | B11: Thailand | C11: 25.2 | D11: 2.9 | E11: 3.2 | F11: 34 | G11: 31.5 | H11: 213.4 | I11: 0.5
A12: 11 | B12: Singapore | C12: 23.2 | D12: 2.9 | E12: 3.1 | F12: 34.2 | G12: 32.4 | H12: 158.4 | I12: 0.6
A13: 12 | B13: Philippines | C13: 22.2 | D13: 3 | E13: 3.5 | F13: 33.1 | G13: 28.5 | H13: 211.5 | I13: 0.5
... A105: 104 | B105: Saudi Arabia | C105: 3.1 | D105: 6.3 | E105: 7.4 | F105: 15.9 | G105: 13.5 | H105: 24 | I105: 4.2

Sheet 2015
A1: Rank | B1: Country | C1: Price To Income Ratio | D1: Gross Rental Yield City Centre | E1: Gross Rental Yield Outside of Centre | F1: Price To Rent Ratio City Centre | G1: Price To Rent Ratio Outside Of City Centre | H1: Mortgage As A Percentage Of Income | I1: Affordability Index
A2: 1 | B2: Uganda | C2: 31.1 | D2: 1.9 | E2: 10 | F2: 53.7 | G2: 10 | H2: 649.4 | I2: 0.2
A3: 2 | B3: Syria | C3: 30.5 | D3: 3.9 | E3: 3.1 | F3: 25.3 | G3: 31.8 | H3: 283.7 | I3: 0.4
A4: 3 | B4: Hong Kong | C4: 30.1 | D4: 2.7 | E4: 2.8 | F4: 37.5 | G4: 36.1 | H4: 193 | I4: 0.5
A5: 4 | B5: Myanmar | C5: 26.8 | D5: 8.5 | E5: 2.9 | F5: 11.8 | G5: 33.9 | H5: 318 | I5: 0.3
A6: 5 | B6: Ghana | C6: 26.6 | D6: 10.8 | E6: 13.4 | F6: 9.3 | G6: 7.4 | H6: 670.4 | I6: 0.1
A7: 6 | B7: China | C7: 26.4 | D7: 2.8 | E7: 3 | F7: 35.9 | G7: 33.3 | H7: 230.6 | I7: 0.4
A8: 7 | B8: El Salvador | C8: 25.4 | D8: 5.3 | E8: 1.7 | F8: 18.9 | G8: 60.3 | H8: 336.1 | I8: 0.3
A9: 8 | B9: Taiwan | C9: 25 | D9: 1.4 | E9: 1.8 | F9: 71.4 | G9: 55.5 | H9: 152.3 | I9: 0.7
A10: 9 | B10: Vietnam | C10: 23.9 | D10: 5.2 | E10: 7.6 | F10: 19.3 | G10: 13.1 | H10: 285.6 | I10: 0.4
A11: 10 | B11: Venezuela | C11: 22.2 | D11: 12.5 | E11: 9.3 | F11: 8 | G11: 10.8 | H11: 333.4 | I11: 0.3
A12: 11 | B12: Mauritius | C12: 22.1 | D12: 2.2 | E12: 2.4 | F12: 45.3 | G12: 41.5 | H12: 228.8 | I12: 0.4
A13: 12 | B13: Singapore | C13: 21.4 | D13: 3.4 | E13: 3.9 | F13: 29.2 | G13: 25.7 | H13: 133.3 | I13: 0.8
... A122: 121 | B122: Tanzania | C122: 1.8 | D122: 80.3 | E122: 27.8 | F122: 1.2 | G122: 3.6 | H122: 27.9 | I122: 3.6

Sheet Sheet3
B1: 2025 | C1: 2025 | D1: 2015 | E1: 2015
A2: Country | B2: GDP per capita | C2: Mortgage as a percentage of Income | D2: GDP per capita | E2: Mortgage as a percentage of Income | I2: Country Name | J2: Country Code | K2: 2024 | M2: Country Name | N2: Country Code | O2: 2015
A3: Albania | B3: =VLOOKUP(A3,$I$3:$K$268,3,FALSE) -> 27146.381 | C3: =VLOOKUP(A3,'2025'!$B$2:$H$105,7,FALSE)/100 -> 1.278 | D3: =VLOOKUP(A3,$M$3:$O$268,3,FALSE) -> 11571.707 | E3: =VLOOKUP(A3,'2015'!$B$2:$H$122,7,FALSE)/100 -> 1.384 | I3: Aruba | J3: ABW | K3: 50649.302 | M3: Aruba | N3: ABW | O3: 35972.86 | Q3: Czech Republic | R3: Czechia
A4: Algeria | B4: =VLOOKUP(A4,$I$3:$K$268,3,FALSE) -> 17620.742 | C4: =VLOOKUP(A4,'2025'!$B$2:$H$105,7,FALSE)/100 -> 1.476 | D4: =VLOOKUP(A4,$M$3:$O$268,3,FALSE) -> 13807.352 | E4: =VLOOKUP(A4,'2015'!$B$2:$H$122,7,FALSE)/100 -> 1.615 | I4: Africa Eastern and Southern | J4: AFE | K4: 4635.7882 | M4: Africa Eastern and Southern | N4: AFE | O4: 3539.8155 | Q4: Egypt | R4: Egypt, Arab Rep.
A5: Argentina | B5: =VLOOKUP(A5,$I$3:$K$268,3,FALSE) -> 30431.193 | C5: =VLOOKUP(A5,'2025'!$B$2:$H$105,7,FALSE)/100 -> 13.504 | D5: =VLOOKUP(A5,$M$3:$O$268,3,FALSE) -> 19899.15 | E5: =VLOOKUP(A5,'2015'!$B$2:$H$122,7,FALSE)/100 -> 2.317 | I5: Afghanistan | J5: AFG | M5: Afghanistan | N5: AFG | O5: 2284.0758 | Q5: Hong Kong (China) | R5: Hong Kong SAR, China
A6: Armenia | B6: =VLOOKUP(A6,$I$3:$K$268,3,FALSE) -> 22823.18 | C6: =VLOOKUP(A6,'2025'!$B$2:$H$105,7,FALSE)/100 -> 3.083 | D6: =VLOOKUP(A6,$M$3:$O$268,3,FALSE) -> 9756.8408 | E6: =VLOOKUP(A6,'2015'!$B$2:$H$122,7,FALSE)/100 -> 1.974 | I6: Africa Western and Central | J6: AFW | K6: 6815.991 | M6: Africa Western and Central | N6: AFW | O6: 5056.7394 | Q6: Iran | R6: Iran, Islamic Rep.
A7: Australia | B7: =VLOOKUP(A7,$I$3:$K$268,3,FALSE) -> 72111.184 | C7: =VLOOKUP(A7,'2025'!$B$2:$H$105,7,FALSE)/100 -> 0.719 | D7: =VLOOKUP(A7,$M$3:$O$268,3,FALSE) -> 46464.587 | E7: =VLOOKUP(A7,'2015'!$B$2:$H$122,7,FALSE)/100 -> 0.593 | I7: Angola | J7: AGO | K7: 10118.609 | M7: Angola | N7: AGO | O7: 8067.4858 | Q7: Kosovo (Disputed Territory)
A8: Austria | B8: =VLOOKUP(A8,$I$3:$K$268,3,FALSE) -> 73911.44 | C8: =VLOOKUP(A8,'2025'!$B$2:$H$105,7,FALSE)/100 -> 0.812 | D8: =VLOOKUP(A8,$M$3:$O$268,3,FALSE) -> 49549.316 | E8: =VLOOKUP(A8,'2015'!$B$2:$H$122,7,FALSE)/100 -> 0.643 | I8: Albania | J8: ALB | K8: 27146.381 | M8: Albania | N8: ALB | O8: 11571.707 | Q8: Kyrgyzstan | R8: Kyrgyz Republic
A9: Azerbaijan | B9: =VLOOKUP(A9,$I$3:$K$268,3,FALSE) -> 25088.999 | C9: =VLOOKUP(A9,'2025'!$B$2:$H$105,7,FALSE)/100 -> 1.678 | D9: =VLOOKUP(A9,$M$3:$O$268,3,FALSE) -> 15075.273 | E9: =VLOOKUP(A9,'2015'!$B$2:$H$122,7,FALSE)/100 -> 1.857 | I9: Andorra | J9: AND | K9: 74939.475 | M9: Andorra | N9: AND | O9: 50733.239 | Q9: Palestine
A10: Bangladesh | B10: =VLOOKUP(A10,$I$3:$K$268,3,FALSE) -> 9646.7698 | C10: =VLOOKUP(A10,'2025'!$B$2:$H$105,7,FALSE)/100 -> 1.471 | D10: =VLOOKUP(A10,$M$3:$O$268,3,FALSE) -> 4212.2358 | E10: =VLOOKUP(A10,'2015'!$B$2:$H$122,7,FALSE)/100 -> 1.94 | I10: Arab World | J10: ARB | K10: 18870.315 | M10: Arab World | N10: ARB | O10: 14332.866 | Q10: Puerto Rico
A11: Belarus | B11: =VLOOKUP(A11,$I$3:$K$268,3,FALSE) -> 33010.331 | C11: =VLOOKUP(A11,'2025'!$B$2:$H$105,7,FALSE)/100 -> 2.047 | D11: =VLOOKUP(A11,$M$3:$O$268,3,FALSE) -> 18133.531 | E11: =VLOOKUP(A11,'2015'!$B$2:$H$122,7,FALSE)/100 -> 5.455 | I11: United Arab Emirates | J11: ARE | K11: 79228.739 | M11: United Arab Emirates | N11: ARE | O11: 73986.064 | Q11: Russia | R11: Russian Federation
A12: Belgium | B12: =VLOOKUP(A12,$I$3:$K$268,3,FALSE) -> 73514.483 | C12: =VLOOKUP(A12,'2025'!$B$2:$H$105,7,FALSE)/100 -> 0.48 | D12: =VLOOKUP(A12,$M$3:$O$268,3,FALSE) -> 46071.915 | E12: =VLOOKUP(A12,'2015'!$B$2:$H$122,7,FALSE)/100 -> 0.459 | I12: Argentina | J12: ARG | K12: 30431.193 | M12: Argentina | N12: ARG | O12: 19899.15 | Q12: Slovakia | R12: Slovak Republic
A13: Bolivia | B13: =VLOOKUP(A13,$I$3:$K$268,3,FALSE) -> 12877.635 | C13: =VLOOKUP(A13,'2025'!$B$2:$H$105,7,FALSE)/100 -> 1.146 | D13: =VLOOKUP(A13,$M$3:$O$268,3,FALSE) -> 8757.3178 | E13: =VLOOKUP(A13,'2015'!$B$2:$H$122,7,FALSE)/100 -> 0.945 | I13: Armenia | J13: ARM | K13: 22823.18 | M13: Armenia | N13: ARM | O13: 9756.8408 | Q13: South Korea | R13: Korea, Rep.
A14: Bosnia And Herzegovina | B14: =VLOOKUP(A14,$I$3:$K$268,3,FALSE) -> 23345.497 | C14: =VLOOKUP(A14,'2025'!$B$2:$H$105,7,FALSE)/100 -> 0.997 | D14: =VLOOKUP(A14,$M$3:$O$268,3,FALSE) -> 11066.154 | E14: =VLOOKUP(A14,'2015'!$B$2:$H$122,7,FALSE)/100 -> 1.237 | I14: American Samoa | J14: ASM | M14: American Samoa | N14: ASM | Q14: Taiwan
A15: Brazil | B15: =VLOOKUP(A15,$I$3:$K$268,3,FALSE) -> 22338.477 | C15: =VLOOKUP(A15,'2025'!$B$2:$H$105,7,FALSE)/100 -> 1.887 | D15: =VLOOKUP(A15,$M$3:$O$268,3,FALSE) -> 14821.438 | E15: =VLOOKUP(A15,'2015'!$B$2:$H$122,7,FALSE)/100 -> 2.006 | I15: Antigua and Barbuda | J15: ATG | K15: 33386.192 | M15: Antigua and Barbuda | N15: ATG | O15: 20985.439 | Q15: Turkey | R15: Turkiye
A16: Bulgaria | B16: =VLOOKUP(A16,$I$3:$K$268,3,FALSE) -> 42224.445 | C16: =VLOOKUP(A16,'2025'!$B$2:$H$105,7,FALSE)/100 -> 0.692 | D16: =VLOOKUP(A16,$M$3:$O$268,3,FALSE) -> 17652.947 | E16: =VLOOKUP(A16,'2015'!$B$2:$H$122,7,FALSE)/100 -> 0.93 | I16: Australia | J16: AUS | K16: 72111.184 | M16: Australia | N16: AUS | O16: 46464.587 | Q16: Venezuela | R16: Venezuela, RB
A17: Cameroon | B17: =VLOOKUP(A17,$I$3:$K$268,3,FALSE) -> 5588.9865 | C17: =VLOOKUP(A17,'2025'!$B$2:$H$105,7,FALSE)/100 -> 9.078 | D17: =VLOOKUP(A17,$M$3:$O$268,3,FALSE) -> 3497.6607 | E17: =VLOOKUP(A17,'2015'!$B$2:$H$122,7,FALSE)/100 -> #N/A | I17: Austria | J17: AUT | K17: 73911.44 | M17: Austria | N17: AUT | O17: 49549.316 | Q17: Vietnam | R17: Viet Nam
A18: Canada | B18: =VLOOKUP(A18,$I$3:$K$268,3,FALSE) -> 64610.38 | C18: =VLOOKUP(A18,'2025'!$B$2:$H$105,7,FALSE)/100 -> 0.921 | D18: =VLOOKUP(A18,$M$3:$O$268,3,FALSE) -> 44668.091 | E18: =VLOOKUP(A18,'2015'!$B$2:$H$122,7,FALSE)/100 -> 0.379 | I18: Azerbaijan | J18: AZE | K18: 25088.999 | M18: Azerbaijan | N18: AZE | O18: 15075.273
A19: Chile | B19: =VLOOKUP(A19,$I$3:$K$268,3,FALSE) -> 36181.157 | C19: =VLOOKUP(A19,'2025'!$B$2:$H$105,7,FALSE)/100 -> 1.263 | D19: =VLOOKUP(A19,$M$3:$O$268,3,FALSE) -> 22468.313 | E19: =VLOOKUP(A19,'2015'!$B$2:$H$122,7,FALSE)/100 -> 0.877 | I19: Burundi | J19: BDI | K19: 1194.9468 | M19: Burundi | N19: BDI | O19: 722.0329
A20: China | B20: =VLOOKUP(A20,$I$3:$K$268,3,FALSE) -> 27104.87 | C20: =VLOOKUP(A20,'2025'!$B$2:$H$105,7,FALSE)/100 -> 2.129 | D20: =VLOOKUP(A20,$M$3:$O$268,3,FALSE) -> 13463.333 | E20: =VLOOKUP(A20,'2015'!$B$2:$H$122,7,FALSE)/100 -> 2.306 | I20: Belgium | J20: BEL | K20: 73514.483 | M20: Belgium | N20: BEL | O20: 46071.915
A21: Colombia | B21: =VLOOKUP(A21,$I$3:$K$268,3,FALSE) -> 22349.436 | C21: =VLOOKUP(A21,'2025'!$B$2:$H$105,7,FALSE)/100 -> 2.618 | D21: =VLOOKUP(A21,$M$3:$O$268,3,FALSE) -> 13332.056 | E21: =VLOOKUP(A21,'2015'!$B$2:$H$122,7,FALSE)/100 -> 1.886 | I21: Benin | J21: BEN | K21: 4434.5642 | M21: Benin | N21: BEN | O21: 2725.3372
A22: Costa Rica | B22: =VLOOKUP(A22,$I$3:$K$268,3,FALSE) -> 31106.764 | C22: =VLOOKUP(A22,'2025'!$B$2:$H$105,7,FALSE)/100 -> 1.225 | D22: =VLOOKUP(A22,$M$3:$O$268,3,FALSE) -> 17525.14 | E22: =VLOOKUP(A22,'2015'!$B$2:$H$122,7,FALSE)/100 -> 0.843 | I22: Burkina Faso | J22: BFA | K22: 2895.8915 | M22: Burkina Faso | N22: BFA | O22: 1691.5794
A23: Croatia | B23: =VLOOKUP(A23,$I$3:$K$268,3,FALSE) -> 49645.746 | C23: =VLOOKUP(A23,'2025'!$B$2:$H$105,7,FALSE)/100 -> 0.958 | D23: =VLOOKUP(A23,$M$3:$O$268,3,FALSE) -> 22187.177 | E23: =VLOOKUP(A23,'2015'!$B$2:$H$122,7,FALSE)/100 -> 1.1 | I23: Bangladesh | J23: BGD | K23: 9646.7698 | M23: Bangladesh | N23: BGD | O23: 4212.2358
A24: Cyprus | B24: =VLOOKUP(A24,$I$3:$K$268,3,FALSE) -> 62312.074 | C24: =VLOOKUP(A24,'2025'!$B$2:$H$105,7,FALSE)/100 -> 0.612 | D24: =VLOOKUP(A24,$M$3:$O$268,3,FALSE) -> 29315.725 | E24: =VLOOKUP(A24,'2015'!$B$2:$H$122,7,FALSE)/100 -> 0.64 | I24: Bulgaria | J24: BGR | K24: 42224.445 | M24: Bulgaria | N24: BGR | O24: 17652.947
A25: Czechia | B25: =VLOOKUP(A25,$I$3:$K$268,3,FALSE) -> 57285.424 | C25: =VLOOKUP(A25,'2025'!$B$2:$H$105,7,FALSE)/100 -> #N/A | D25: =VLOOKUP(A25,$M$3:$O$268,3,FALSE) -> 34093.028 | E25: =VLOOKUP(A25,'2015'!$B$2:$H$122,7,FALSE)/100 -> #N/A | I25: Bahrain | J25: BHR | K25: 66941.243 | M25: Bahrain | N25: BHR | O25: 48034.247
A26: Denmark | B26: =VLOOKUP(A26,$I$3:$K$268,3,FALSE) -> 81878.235 | C26: =VLOOKUP(A26,'2025'!$B$2:$H$105,7,FALSE)/100 -> 0.481 | D26: =VLOOKUP(A26,$M$3:$O$268,3,FALSE) -> 48897.21 | E26: =VLOOKUP(A26,'2015'!$B$2:$H$122,7,FALSE)/100 -> 0.343 | I26: Bahamas, The | J26: BHS | K26: 41197.934 | M26: Bahamas, The | N26: BHS | O26: 32137.578
A27: Dominican Republic | B27: =VLOOKUP(A27,$I$3:$K$268,3,FALSE) -> 27541.663 | C27: =VLOOKUP(A27,'2025'!$B$2:$H$105,7,FALSE)/100 -> 2.349 | D27: =VLOOKUP(A27,$M$3:$O$268,3,FALSE) -> 14804.097 | E27: =VLOOKUP(A27,'2015'!$B$2:$H$122,7,FALSE)/100 -> 1.719 | I27: Bosnia and Herzegovina | J27: BIH | K27: 23345.497 | M27: Bosnia and Herzegovina | N27: BIH | O27: 11066.154
A28: Ecuador | B28: =VLOOKUP(A28,$I$3:$K$268,3,FALSE) -> 15840.267 | C28: =VLOOKUP(A28,'2025'!$B$2:$H$105,7,FALSE)/100 -> 1.375 | D28: =VLOOKUP(A28,$M$3:$O$268,3,FALSE) -> 10877.751 | E28: =VLOOKUP(A28,'2015'!$B$2:$H$122,7,FALSE)/100 -> 1.677 | I28: Belarus | J28: BLR | K28: 33010.331 | M28: Belarus | N28: BLR | O28: 18133.531
A29: Egypt, Arab Rep. | B29: =VLOOKUP(A29,$I$3:$K$268,3,FALSE) -> 19094.145 | C29: =VLOOKUP(A29,'2025'!$B$2:$H$105,7,FALSE)/100 -> #N/A | D29: =VLOOKUP(A29,$M$3:$O$268,3,FALSE) -> 10903.337 | E29: =VLOOKUP(A29,'2015'!$B$2:$H$122,7,FALSE)/100 -> #N/A | I29: Belize | J29: BLZ | K29: 14346.519 | M29: Belize | N29: BLZ | O29: 9538.3869
... A34: France | B34: =VLOOKUP(A34,$I$3:$K$268,3,FALSE) -> 62556.918 | C34: =VLOOKUP(A34,'2025'!$B$2:$H$105,7,FALSE)/100 -> 0.725 | D34: =VLOOKUP(A34,$M$3:$O$268,3,FALSE) -> 40905.177 | E34: =VLOOKUP(A34,'2015'!$B$2:$H$122,7,FALSE)/100 -> 0.667 | I34: Brunei Darussalam | J34: BRN | K34: 89879.361 | M34: Brunei Darussalam | N34: BRN | O34: 62707.826
A35: Georgia | B35: =VLOOKUP(A35,$I$3:$K$268,3,FALSE) -> 28285.073 | C35: =VLOOKUP(A35,'2025'!$B$2:$H$105,7,FALSE)/100 -> 1.654 | D35: =VLOOKUP(A35,$M$3:$O$268,3,FALSE) -> 12269.653 | E35: =VLOOKUP(A35,'2015'!$B$2:$H$122,7,FALSE)/100 -> 2.086 | I35: Bhutan | J35: BTN | M35: Bhutan | N35: BTN | O35: 10213.814
A36: Germany | B36: =VLOOKUP(A36,$I$3:$K$268,3,FALSE) -> 73551.935 | C36: =VLOOKUP(A36,'2025'!$B$2:$H$105,7,FALSE)/100 -> 0.646 | D36: =VLOOKUP(A36,$M$3:$O$268,3,FALSE) -> 48545.401 | E36: =VLOOKUP(A36,'2015'!$B$2:$H$122,7,FALSE)/100 -> 0.443 | I36: Botswana | J36: BWA | K36: 20538.132 | M36: Botswana | N36: BWA | O36: 14143.694
A37: Greece | B37: =VLOOKUP(A37,$I$3:$K$268,3,FALSE) -> 44327.21 | C37: =VLOOKUP(A37,'2025'!$B$2:$H$105,7,FALSE)/100 -> 0.992 | D37: =VLOOKUP(A37,$M$3:$O$268,3,FALSE) -> 26607.726 | E37: =VLOOKUP(A37,'2015'!$B$2:$H$122,7,FALSE)/100 -> 0.753 | I37: Central African Republic | J37: CAF | K37: 1263.1023 | M37: Central African Republic | N37: CAF | O37: 768.87089
A38: Hong Kong SAR, China | B38: =VLOOKUP(A38,$I$3:$K$268,3,FALSE) -> 75195.987 | C38: =VLOOKUP(A38,'2025'!$B$2:$H$105,7,FALSE)/100 -> #N/A | D38: =VLOOKUP(A38,$M$3:$O$268,3,FALSE) -> 56043.043 | E38: =VLOOKUP(A38,'2015'!$B$2:$H$122,7,FALSE)/100 -> #N/A | I38: Canada | J38: CAN | K38: 64610.38 | M38: Canada | N38: CAN | O38: 44668.091
A39: Hungary | B39: =VLOOKUP(A39,$I$3:$K$268,3,FALSE) -> 48552.471 | C39: =VLOOKUP(A39,'2025'!$B$2:$H$105,7,FALSE)/100 -> 1.271 | D39: =VLOOKUP(A39,$M$3:$O$268,3,FALSE) -> 26937.732 | E39: =VLOOKUP(A39,'2015'!$B$2:$H$122,7,FALSE)/100 -> 0.84 | I39: Central Europe and the Baltics | J39: CEB | K39: 50599.212 | M39: Central Europe and the Baltics | N39: CEB | O39: 25780.239
A40: Iceland | B40: =VLOOKUP(A40,$I$3:$K$268,3,FALSE) -> 84256.845 | C40: =VLOOKUP(A40,'2025'!$B$2:$H$105,7,FALSE)/100 -> 0.746 | D40: =VLOOKUP(A40,$M$3:$O$268,3,FALSE) -> 49201.064 | E40: =VLOOKUP(A40,'2015'!$B$2:$H$122,7,FALSE)/100 -> 0.527 | I40: Switzerland | J40: CHE | K40: 96497.695 | M40: Switzerland | N40: CHE | O40: 65265.046
A41: India | B41: =VLOOKUP(A41,$I$3:$K$268,3,FALSE) -> 11159.986 | C41: =VLOOKUP(A41,'2025'!$B$2:$H$105,7,FALSE)/100 -> 1.177 | D41: =VLOOKUP(A41,$M$3:$O$268,3,FALSE) -> 5425.036 | E41: =VLOOKUP(A41,'2015'!$B$2:$H$122,7,FALSE)/100 -> 1.244 | I41: Channel Islands | J41: CHI | M41: Channel Islands | N41: CHI
A42: Indonesia | B42: =VLOOKUP(A42,$I$3:$K$268,3,FALSE) -> 16448.276 | C42: =VLOOKUP(A42,'2025'!$B$2:$H$105,7,FALSE)/100 -> 1.633 | D42: =VLOOKUP(A42,$M$3:$O$268,3,FALSE) -> 10027.537 | E42: =VLOOKUP(A42,'2015'!$B$2:$H$122,7,FALSE)/100 -> 2.174 | I42: Chile | J42: CHL | K42: 36181.157 | M42: Chile | N42: CHL | O42: 22468.313
A43: Iran, Islamic Rep. | B43: =VLOOKUP(A43,$I$3:$K$268,3,FALSE) -> 19873.886 | C43: =VLOOKUP(A43,'2025'!$B$2:$H$105,7,FALSE)/100 -> #N/A | D43: =VLOOKUP(A43,$M$3:$O$268,3,FALSE) -> 14273.55 | E43: =VLOOKUP(A43,'2015'!$B$2:$H$122,7,FALSE)/100 -> #N/A | I43: China | J43: CHN | K43: 27104.87 | M43: China | N43: CHN | O43: 13463.333
A44: Iraq | B44: =VLOOKUP(A44,$I$3:$K$268,3,FALSE) -> 14464.319 | C44: =VLOOKUP(A44,'2025'!$B$2:$H$105,7,FALSE)/100 -> 0.869 | D44: =VLOOKUP(A44,$M$3:$O$268,3,FALSE) -> 9334.466 | E44: =VLOOKUP(A44,'2015'!$B$2:$H$122,7,FALSE)/100 -> 0.932 | I44: Cote d'Ivoire | J44: CIV | K44: 7669.232 | M44: Cote d'Ivoire | N44: CIV | O44: 4403.643
A45: Ireland | B45: =VLOOKUP(A45,$I$3:$K$268,3,FALSE) -> 133437.47 | C45: =VLOOKUP(A45,'2025'!$B$2:$H$105,7,FALSE)/100 -> 0.511 | D45: =VLOOKUP(A45,$M$3:$O$268,3,FALSE) -> 71588.266 | E45: =VLOOKUP(A45,'2015'!$B$2:$H$122,7,FALSE)/100 -> 0.45 | I45: Cameroon | J45: CMR | K45: 5588.9865 | M45: Cameroon | N45: CMR | O45: 3497.6607
A46: Israel | B46: =VLOOKUP(A46,$I$3:$K$268,3,FALSE) -> 57235.776 | C46: =VLOOKUP(A46,'2025'!$B$2:$H$105,7,FALSE)/100 -> 1.065 | D46: =VLOOKUP(A46,$M$3:$O$268,3,FALSE) -> 35870.793 | E46: =VLOOKUP(A46,'2015'!$B$2:$H$122,7,FALSE)/100 -> 0.689 | I46: Congo, Dem. Rep. | J46: COD | K46: 1821.0487 | M46: Congo, Dem. Rep. | N46: COD | O46: 910.39313
A47: Italy | B47: =VLOOKUP(A47,$I$3:$K$268,3,FALSE) -> 62014.268 | C47: =VLOOKUP(A47,'2025'!$B$2:$H$105,7,FALSE)/100 -> 0.727 | D47: =VLOOKUP(A47,$M$3:$O$268,3,FALSE) -> 37384.38 | E47: =VLOOKUP(A47,'2015'!$B$2:$H$122,7,FALSE)/100 -> 0.941 | I47: Congo, Rep. | J47: COG | K47: 7026.3622 | M47: Congo, Rep. | N47: COG | O47: 4715.1343
A48: Japan | B48: =VLOOKUP(A48,$I$3:$K$268,3,FALSE) -> 52039.172 | C48: =VLOOKUP(A48,'2025'!$B$2:$H$105,7,FALSE)/100 -> 0.729 | D48: =VLOOKUP(A48,$M$3:$O$268,3,FALSE) -> 40898.807 | E48: =VLOOKUP(A48,'2015'!$B$2:$H$122,7,FALSE)/100 -> 0.558 | I48: Colombia | J48: COL | K48: 22349.436 | M48: Colombia | N48: COL | O48: 13332.056
A49: Jordan | B49: =VLOOKUP(A49,$I$3:$K$268,3,FALSE) -> 10821.491 | C49: =VLOOKUP(A49,'2025'!$B$2:$H$105,7,FALSE)/100 -> 0.673 | D49: =VLOOKUP(A49,$M$3:$O$268,3,FALSE) -> 8967.08 | E49: =VLOOKUP(A49,'2015'!$B$2:$H$122,7,FALSE)/100 -> 0.875 | I49: Comoros | J49: COM | K49: 3958.5323 | M49: Comoros | N49: COM | O49: 2949.4734
A50: Kazakhstan | B50: =VLOOKUP(A50,$I$3:$K$268,3,FALSE) -> 40890.932 | C50: =VLOOKUP(A50,'2025'!$B$2:$H$105,7,FALSE)/100 -> 1.773 | D50: =VLOOKUP(A50,$M$3:$O$268,3,FALSE) -> 22484.365 | E50: =VLOOKUP(A50,'2015'!$B$2:$H$122,7,FALSE)/100 -> 1.867 | I50: Cabo Verde | J50: CPV | K50: 11195.121 | M50: Cabo Verde | N50: CPV | O50: 6773.4868
A51: Korea, Rep. | B51: =VLOOKUP(A51,$I$3:$K$268,3,FALSE) -> 61051.349 | C51: =VLOOKUP(A51,'2025'!$B$2:$H$105,7,FALSE)/100 -> #N/A | D51: =VLOOKUP(A51,$M$3:$O$268,3,FALSE) -> 39794.196 | E51: =VLOOKUP(A51,'2015'!$B$2:$H$122,7,FALSE)/100 -> #N/A | I51: Costa Rica | J51: CRI | K51: 31106.764 | M51: Costa Rica | N51: CRI | O51: 17525.14
A52: Kuwait | B52: =VLOOKUP(A52,$I$3:$K$268,3,FALSE) -> 52443.597 | C52: =VLOOKUP(A52,'2025'!$B$2:$H$105,7,FALSE)/100 -> 0.607 | D52: =VLOOKUP(A52,$M$3:$O$268,3,FALSE) -> 45267.309 | E52: =VLOOKUP(A52,'2015'!$B$2:$H$122,7,FALSE)/100 -> 0.547 | I52: Caribbean small states | J52: CSS | K52: 38624.061 | M52: Caribbean small states | N52: CSS | O52: 20632.338
A53: Kyrgyz Republic | B53: =VLOOKUP(A53,$I$3:$K$268,3,FALSE) -> 8012.4546 | C53: =VLOOKUP(A53,'2025'!$B$2:$H$105,7,FALSE)/100 -> #N/A | D53: =VLOOKUP(A53,$M$3:$O$268,3,FALSE) -> 4153.3767 | E53: =VLOOKUP(A53,'2015'!$B$2:$H$122,7,FALSE)/100 -> #N/A | I53: Cuba | J53: CUB | M53: Cuba | N53: CUB
A54: Latvia | B54: =VLOOKUP(A54,$I$3:$K$268,3,FALSE) -> 43394.273 | C54: =VLOOKUP(A54,'2025'!$B$2:$H$105,7,FALSE)/100 -> 0.641 | D54: =VLOOKUP(A54,$M$3:$O$268,3,FALSE) -> 22543.918 | E54: =VLOOKUP(A54,'2015'!$B$2:$H$122,7,FALSE)/100 -> 0.835 | I54: Curacao | J54: CUW | K54: 32693.294 | M54: Curacao | N54: CUW | O54: 24037.649
A55: Lithuania | B55: =VLOOKUP(A55,$I$3:$K$268,3,FALSE) -> 55285.899 | C55: =VLOOKUP(A55,'2025'!$B$2:$H$105,7,FALSE)/100 -> 0.919 | D55: =VLOOKUP(A55,$M$3:$O$268,3,FALSE) -> 26948.592 | E55: =VLOOKUP(A55,'2015'!$B$2:$H$122,7,FALSE)/100 -> 0.875 | I55: Cayman Islands | J55: CYM | M55: Cayman Islands | N55: CYM | O55: 64009.317
A56: Luxembourg | B56: =VLOOKUP(A56,$I$3:$K$268,3,FALSE) -> 155941.29 | C56: =VLOOKUP(A56,'2025'!$B$2:$H$105,7,FALSE)/100 -> 0.587 | D56: =VLOOKUP(A56,$M$3:$O$268,3,FALSE) -> 107859.69 | E56: =VLOOKUP(A56,'2015'!$B$2:$H$122,7,FALSE)/100 -> 0.504 | I56: Cyprus | J56: CYP | K56: 62312.074 | M56: Cyprus | N56: CYP | O56: 29315.725
A57: Malaysia | B57: =VLOOKUP(A57,$I$3:$K$268,3,FALSE) -> 38779.283 | C57: =VLOOKUP(A57,'2025'!$B$2:$H$105,7,FALSE)/100 -> 0.641 | D57: =VLOOKUP(A57,$M$3:$O$268,3,FALSE) -> 24526.394 | E57: =VLOOKUP(A57,'2015'!$B$2:$H$122,7,FALSE)/100 -> 0.648 | I57: Czechia | J57: CZE | K57: 57285.424 | M57: Czechia | N57: CZE | O57: 34093.028
A58: Malta | B58: =VLOOKUP(A58,$I$3:$K$268,3,FALSE) -> 71017.774 | C58: =VLOOKUP(A58,'2025'!$B$2:$H$105,7,FALSE)/100 -> 0.861 | D58: =VLOOKUP(A58,$M$3:$O$268,3,FALSE) -> 35844.479 | E58: =VLOOKUP(A58,'2015'!$B$2:$H$122,7,FALSE)/100 -> 0.498 | I58: Germany | J58: DEU | K58: 73551.935 | M58: Germany | N58: DEU | O58: 48545.401
A59: Mauritius | B59: =VLOOKUP(A59,$I$3:$K$268,3,FALSE) -> 31839.76 | C59: =VLOOKUP(A59,'2025'!$B$2:$H$105,7,FALSE)/100 -> 1.592 | D59: =VLOOKUP(A59,$M$3:$O$268,3,FALSE) -> 20269.524 | E59: =VLOOKUP(A59,'2015'!$B$2:$H$122,7,FALSE)/100 -> 2.288 | I59: Djibouti | J59: DJI | K59: 7810.2787 | M59: Djibouti | N59: DJI | O59: 4263.9629
A60: Mexico | B60: =VLOOKUP(A60,$I$3:$K$268,3,FALSE) -> 26185.356 | C60: =VLOOKUP(A60,'2025'!$B$2:$H$105,7,FALSE)/100 -> 1.5 | D60: =VLOOKUP(A60,$M$3:$O$268,3,FALSE) -> 19071.444 | E60: =VLOOKUP(A60,'2015'!$B$2:$H$122,7,FALSE)/100 -> 0.773 | I60: Dominica | J60: DMA | K60: 21300.685 | M60: Dominica | N60: DMA | O60: 12092.732
A61: Moldova | B61: =VLOOKUP(A61,$I$3:$K$268,3,FALSE) -> 18614.988 | C61: =VLOOKUP(A61,'2025'!$B$2:$H$105,7,FALSE)/100 -> 1.495 | D61: =VLOOKUP(A61,$M$3:$O$268,3,FALSE) -> 9197.6184 | E61: =VLOOKUP(A61,'2015'!$B$2:$H$122,7,FALSE)/100 -> 2.673 | I61: Denmark | J61: DNK | K61: 81878.235 | M61: Denmark | N61: DNK | O61: 48897.21
A62: Montenegro | B62: =VLOOKUP(A62,$I$3:$K$268,3,FALSE) -> 34806.948 | C62: =VLOOKUP(A62,'2025'!$B$2:$H$105,7,FALSE)/100 -> 1.097 | D62: =VLOOKUP(A62,$M$3:$O$268,3,FALSE) -> 15033.061 | E62: =VLOOKUP(A62,'2015'!$B$2:$H$122,7,FALSE)/100 -> 1.702 | I62: Dominican Republic | J62: DOM | K62: 27541.663 | M62: Dominican Republic | N62: DOM | O62: 14804.097
A63: Morocco | B63: =VLOOKUP(A63,$I$3:$K$268,3,FALSE) -> 10415.124 | C63: =VLOOKUP(A63,'2025'!$B$2:$H$105,7,FALSE)/100 -> 1.058 | D63: =VLOOKUP(A63,$M$3:$O$268,3,FALSE) -> 7799.0923 | E63: =VLOOKUP(A63,'2015'!$B$2:$H$122,7,FALSE)/100 -> 1.36 | I63: Algeria | J63: DZA | K63: 17620.742 | M63: Algeria | N63: DZA | O63: 13807.352
A64: Nepal | B64: =VLOOKUP(A64,$I$3:$K$268,3,FALSE) -> 5736.6213 | C64: =VLOOKUP(A64,'2025'!$B$2:$H$105,7,FALSE)/100 -> 4.474 | D64: =VLOOKUP(A64,$M$3:$O$268,3,FALSE) -> 2957.3056 | E64: =VLOOKUP(A64,'2015'!$B$2:$H$122,7,FALSE)/100 -> 2.574 | I64: East Asia & Pacific (excluding high income) | J64: EAP | K64: 23248.025 | M64: East Asia & Pacific (excluding high income) | N64: EAP | O64: 12146.381
A65: Netherlands | B65: =VLOOKUP(A65,$I$3:$K$268,3,FALSE) -> 86173.629 | C65: =VLOOKUP(A65,'2025'!$B$2:$H$105,7,FALSE)/100 -> 0.572 | D65: =VLOOKUP(A65,$M$3:$O$268,3,FALSE) -> 50956.693 | E65: =VLOOKUP(A65,'2015'!$B$2:$H$122,7,FALSE)/100 -> 0.461 | I65: Early-demographic dividend | J65: EAR | K65: 13995.406 | M65: Early-demographic dividend | N65: EAR | O65: 8319.9135
A66: New Zealand | B66: =VLOOKUP(A66,$I$3:$K$268,3,FALSE) -> 55551.144 | C66: =VLOOKUP(A66,'2025'!$B$2:$H$105,7,FALSE)/100 -> 0.67 | D66: =VLOOKUP(A66,$M$3:$O$268,3,FALSE) -> 37513.296 | E66: =VLOOKUP(A66,'2015'!$B$2:$H$122,7,FALSE)/100 -> 0.491 | I66: East Asia & Pacific | J66: EAS | K66: 27285.211 | M66: East Asia & Pacific | N66: EAS | O66: 15476.317
A67: North Macedonia | B67: =VLOOKUP(A67,$I$3:$K$268,3,FALSE) -> 26986.569 | C67: =VLOOKUP(A67,'2025'!$B$2:$H$105,7,FALSE)/100 -> 0.965 | D67: =VLOOKUP(A67,$M$3:$O$268,3,FALSE) -> 14045.071 | E67: =VLOOKUP(A67,'2015'!$B$2:$H$122,7,FALSE)/100 -> 1.481 | I67: Europe & Central Asia (excluding high income) | J67: ECA | K67: 29316.46 | M67: Europe & Central Asia (excluding high income) | N67: ECA | O67: 16016.953
... A71: Panama | B71: =VLOOKUP(A71,$I$3:$K$268,3,FALSE) -> 41369.423 | C71: =VLOOKUP(A71,'2025'!$B$2:$H$105,7,FALSE)/100 -> 0.988 | D71: =VLOOKUP(A71,$M$3:$O$268,3,FALSE) -> 27245.279 | E71: =VLOOKUP(A71,'2015'!$B$2:$H$122,7,FALSE)/100 -> 0.888 | I71: Euro area | J71: EMU | K71: 66098.011 | M71: Euro area | N71: EMU | O71: 41183.56
A72: Peru | B72: =VLOOKUP(A72,$I$3:$K$268,3,FALSE) -> 17802.418 | C72: =VLOOKUP(A72,'2025'!$B$2:$H$105,7,FALSE)/100 -> 2.184 | D72: =VLOOKUP(A72,$M$3:$O$268,3,FALSE) -> 11600.387 | E72: =VLOOKUP(A72,'2015'!$B$2:$H$122,7,FALSE)/100 -> 1.898 | I72: Eritrea | J72: ERI | M72: Eritrea | N72: ERI
A73: Philippines | B73: =VLOOKUP(A73,$I$3:$K$268,3,FALSE) -> 11794.138 | C73: =VLOOKUP(A73,'2025'!$B$2:$H$105,7,FALSE)/100 -> 2.115 | D73: =VLOOKUP(A73,$M$3:$O$268,3,FALSE) -> 6894.267 | E73: =VLOOKUP(A73,'2015'!$B$2:$H$122,7,FALSE)/100 -> 1.986 | I73: Spain | J73: ESP | K73: 57965.295 | M73: Spain | N73: ESP | O73: 35228.633
A74: Poland | B74: =VLOOKUP(A74,$I$3:$K$268,3,FALSE) -> 51262.511 | C74: =VLOOKUP(A74,'2025'!$B$2:$H$105,7,FALSE)/100 -> 1.021 | D74: =VLOOKUP(A74,$M$3:$O$268,3,FALSE) -> 26988.107 | E74: =VLOOKUP(A74,'2015'!$B$2:$H$122,7,FALSE)/100 -> 0.831 | I74: Estonia | J74: EST | K74: 49968.711 | M74: Estonia | N74: EST | O74: 29712.63
A75: Portugal | B75: =VLOOKUP(A75,$I$3:$K$268,3,FALSE) -> 51679.888 | C75: =VLOOKUP(A75,'2025'!$B$2:$H$105,7,FALSE)/100 -> 1.155 | D75: =VLOOKUP(A75,$M$3:$O$268,3,FALSE) -> 29608.007 | E75: =VLOOKUP(A75,'2015'!$B$2:$H$122,7,FALSE)/100 -> 0.619 | I75: Ethiopia | J75: ETH | K75: 3287.5349 | M75: Ethiopia | N75: ETH | O75: 1632.6182
A76: Qatar | B76: =VLOOKUP(A76,$I$3:$K$268,3,FALSE) -> 126046.35 | C76: =VLOOKUP(A76,'2025'!$B$2:$H$105,7,FALSE)/100 -> 0.422 | D76: =VLOOKUP(A76,$M$3:$O$268,3,FALSE) -> 102545.86 | E76: =VLOOKUP(A76,'2015'!$B$2:$H$122,7,FALSE)/100 -> 0.517 | I76: European Union | J76: EUU | K76: 63610.227 | M76: European Union | N76: EUU | O76: 38444.682
A77: Romania | B77: =VLOOKUP(A77,$I$3:$K$268,3,FALSE) -> 49558.669 | C77: =VLOOKUP(A77,'2025'!$B$2:$H$105,7,FALSE)/100 -> 0.952 | D77: =VLOOKUP(A77,$M$3:$O$268,3,FALSE) -> 20201.858 | E77: =VLOOKUP(A77,'2015'!$B$2:$H$122,7,FALSE)/100 -> 1.09 | I77: Fragile and conflict affected situations | J77: FCS | K77: 6394.5659 | M77: Fragile and conflict affected situations | N77: FCS | O77: 4942.5258
A78: Russian Federation | B78: =VLOOKUP(A78,$I$3:$K$268,3,FALSE) -> 47404.965 | C78: =VLOOKUP(A78,'2025'!$B$2:$H$105,7,FALSE)/100 -> #N/A | D78: =VLOOKUP(A78,$M$3:$O$268,3,FALSE) -> 23994.014 | E78: =VLOOKUP(A78,'2015'!$B$2:$H$122,7,FALSE)/100 -> #N/A | I78: Finland | J78: FIN | K78: 65378.384 | M78: Finland | N78: FIN | O78: 42257.859
A79: Saudi Arabia | B79: =VLOOKUP(A79,$I$3:$K$268,3,FALSE) -> 71375.373 | C79: =VLOOKUP(A79,'2025'!$B$2:$H$105,7,FALSE)/100 -> 0.24 | D79: =VLOOKUP(A79,$M$3:$O$268,3,FALSE) -> 53930.827 | E79: =VLOOKUP(A79,'2015'!$B$2:$H$122,7,FALSE)/100 -> 0.235 | I79: Fiji | J79: FJI | K79: 15450.299 | M79: Fiji | N79: FJI | O79: 11519.301
A80: Serbia | B80: =VLOOKUP(A80,$I$3:$K$268,3,FALSE) -> 32781.014 | C80: =VLOOKUP(A80,'2025'!$B$2:$H$105,7,FALSE)/100 -> 1.465 | D80: =VLOOKUP(A80,$M$3:$O$268,3,FALSE) -> 14523.539 | E80: =VLOOKUP(A80,'2015'!$B$2:$H$122,7,FALSE)/100 -> 1.553 | I80: France | J80: FRA | K80: 62556.918 | M80: France | N80: FRA | O80: 40905.177
A81: Singapore | B81: =VLOOKUP(A81,$I$3:$K$268,3,FALSE) -> 150689.3 | C81: =VLOOKUP(A81,'2025'!$B$2:$H$105,7,FALSE)/100 -> 1.584 | D81: =VLOOKUP(A81,$M$3:$O$268,3,FALSE) -> 87156.187 | E81: =VLOOKUP(A81,'2015'!$B$2:$H$122,7,FALSE)/100 -> 1.333 | I81: Faroe Islands | J81: FRO | K81: 81908.778 | M81: Faroe Islands | N81: FRO | O81: 53684.367
A82: Slovak Republic | B82: =VLOOKUP(A82,$I$3:$K$268,3,FALSE) -> 48132.356 | C82: =VLOOKUP(A82,'2025'!$B$2:$H$105,7,FALSE)/100 -> #N/A | D82: =VLOOKUP(A82,$M$3:$O$268,3,FALSE) -> 30147.99 | E82: =VLOOKUP(A82,'2015'!$B$2:$H$122,7,FALSE)/100 -> #N/A | I82: Micronesia, Fed. Sts. | J82: FSM | K82: 4346.8425 | M82: Micronesia, Fed. Sts. | N82: FSM | O82: 3288.9216
A83: Slovenia | B83: =VLOOKUP(A83,$I$3:$K$268,3,FALSE) -> 57186.371 | C83: =VLOOKUP(A83,'2025'!$B$2:$H$105,7,FALSE)/100 -> 0.94 | D83: =VLOOKUP(A83,$M$3:$O$268,3,FALSE) -> 31336.204 | E83: =VLOOKUP(A83,'2015'!$B$2:$H$122,7,FALSE)/100 -> 0.796 | I83: Gabon | J83: GAB | K83: 21510.173 | M83: Gabon | N83: GAB | O83: 14306.434
A84: South Africa | B84: =VLOOKUP(A84,$I$3:$K$268,3,FALSE) -> 15456.199 | C84: =VLOOKUP(A84,'2025'!$B$2:$H$105,7,FALSE)/100 -> 0.416 | D84: =VLOOKUP(A84,$M$3:$O$268,3,FALSE) -> 13397.523 | E84: =VLOOKUP(A84,'2015'!$B$2:$H$122,7,FALSE)/100 -> 0.336 | I84: United Kingdom | J84: GBR | K84: 62009.491 | M84: United Kingdom | N84: GBR | O84: 42515.279
... A86: Sri Lanka | B86: =VLOOKUP(A86,$I$3:$K$268,3,FALSE) -> 15632.592 | C86: =VLOOKUP(A86,'2025'!$B$2:$H$105,7,FALSE)/100 -> 6.035 | D86: =VLOOKUP(A86,$M$3:$O$268,3,FALSE) -> 12227.171 | E86: =VLOOKUP(A86,'2015'!$B$2:$H$122,7,FALSE)/100 -> 2.261 | I86: Ghana | J86: GHA | K86: 8019.997 | M86: Ghana | N86: GHA | O86: 5191.3705
A87: Sweden | B87: =VLOOKUP(A87,$I$3:$K$268,3,FALSE) -> 71844.913 | C87: =VLOOKUP(A87,'2025'!$B$2:$H$105,7,FALSE)/100 -> 0.586 | D87: =VLOOKUP(A87,$M$3:$O$268,3,FALSE) -> 48772.07 | E87: =VLOOKUP(A87,'2015'!$B$2:$H$122,7,FALSE)/100 -> 0.619 | I87: Gibraltar | J87: GIB | M87: Gibraltar | N87: GIB
A88: Switzerland | B88: =VLOOKUP(A88,$I$3:$K$268,3,FALSE) -> 96497.695 | C88: =VLOOKUP(A88,'2025'!$B$2:$H$105,7,FALSE)/100 -> 0.696 | D88: =VLOOKUP(A88,$M$3:$O$268,3,FALSE) -> 65265.046 | E88: =VLOOKUP(A88,'2015'!$B$2:$H$122,7,FALSE)/100 -> 0.44 | I88: Guinea | J88: GIN | K88: 4565.3008 | M88: Guinea | N88: GIN | O88: 1929.6809
A89: Thailand | B89: =VLOOKUP(A89,$I$3:$K$268,3,FALSE) -> 24712.066 | C89: =VLOOKUP(A89,'2025'!$B$2:$H$105,7,FALSE)/100 -> 2.134 | D89: =VLOOKUP(A89,$M$3:$O$268,3,FALSE) -> 15791.171 | E89: =VLOOKUP(A89,'2015'!$B$2:$H$122,7,FALSE)/100 -> 1.795 | I89: Gambia, The | J89: GMB | K89: 3475.6125 | M89: Gambia, The | N89: GMB | O89: 1990.3163
A90: Tunisia | B90: =VLOOKUP(A90,$I$3:$K$268,3,FALSE) -> 14521.008 | C90: =VLOOKUP(A90,'2025'!$B$2:$H$105,7,FALSE)/100 -> 1.532 | D90: =VLOOKUP(A90,$M$3:$O$268,3,FALSE) -> 10782.544 | E90: =VLOOKUP(A90,'2015'!$B$2:$H$122,7,FALSE)/100 -> 1.093 | I90: Guinea-Bissau | J90: GNB | K90: 3119.3716 | M90: Guinea-Bissau | N90: GNB | O90: 1729.9426
A91: Turkiye | B91: =VLOOKUP(A91,$I$3:$K$268,3,FALSE) -> 45639.019 | C91: =VLOOKUP(A91,'2025'!$B$2:$H$105,7,FALSE)/100 -> #N/A | D91: =VLOOKUP(A91,$M$3:$O$268,3,FALSE) -> 25890.055 | E91: =VLOOKUP(A91,'2015'!$B$2:$H$122,7,FALSE)/100 -> #N/A | I91: Equatorial Guinea | J91: GNQ | K91: 17566.76 | M91: Equatorial Guinea | N91: GNQ | O91: 19478.701
A92: Ukraine | B92: =VLOOKUP(A92,$I$3:$K$268,3,FALSE) -> 18550.463 | C92: =VLOOKUP(A92,'2025'!$B$2:$H$105,7,FALSE)/100 -> 2.533 | D92: =VLOOKUP(A92,$M$3:$O$268,3,FALSE) -> 9921.834 | E92: =VLOOKUP(A92,'2015'!$B$2:$H$122,7,FALSE)/100 -> 3.493 | I92: Greece | J92: GRC | K92: 44327.21 | M92: Greece | N92: GRC | O92: 26607.726
A93: United Arab Emirates | B93: =VLOOKUP(A93,$I$3:$K$268,3,FALSE) -> 79228.739 | C93: =VLOOKUP(A93,'2025'!$B$2:$H$105,7,FALSE)/100 -> 0.539 | D93: =VLOOKUP(A93,$M$3:$O$268,3,FALSE) -> 73986.064 | E93: =VLOOKUP(A93,'2015'!$B$2:$H$122,7,FALSE)/100 -> 0.499 | I93: Grenada | J93: GRD | K93: 20177.809 | M93: Grenada | N93: GRD | O93: 13214.41
A94: United Kingdom | B94: =VLOOKUP(A94,$I$3:$K$268,3,FALSE) -> 62009.491 | C94: =VLOOKUP(A94,'2025'!$B$2:$H$105,7,FALSE)/100 -> 0.742 | D94: =VLOOKUP(A94,$M$3:$O$268,3,FALSE) -> 42515.279 | E94: =VLOOKUP(A94,'2015'!$B$2:$H$122,7,FALSE)/100 -> 0.634 | I94: Greenland | J94: GRL | M94: Greenland | N94: GRL | O94: 55815.65
A95: United States | B95: =VLOOKUP(A95,$I$3:$K$268,3,FALSE) -> 85809.9 | C95: =VLOOKUP(A95,'2025'!$B$2:$H$105,7,FALSE)/100 -> 0.301 | D95: =VLOOKUP(A95,$M$3:$O$268,3,FALSE) -> 56849.47 | E95: =VLOOKUP(A95,'2015'!$B$2:$H$122,7,FALSE)/100 -> 0.194 | I95: Guatemala | J95: GTM | K95: 14368.661 | M95: Guatemala | N95: GTM | O95: 8934.0026
A96: Uruguay | B96: =VLOOKUP(A96,$I$3:$K$268,3,FALSE) -> 36417.874 | C96: =VLOOKUP(A96,'2025'!$B$2:$H$105,7,FALSE)/100 -> 1.141 | D96: =VLOOKUP(A96,$M$3:$O$268,3,FALSE) -> 22168.611 | E96: =VLOOKUP(A96,'2015'!$B$2:$H$122,7,FALSE)/100 -> 1.085 | I96: Guam | J96: GUM | M96: Guam | N96: GUM
A97: Uzbekistan | B97: =VLOOKUP(A97,$I$3:$K$268,3,FALSE) -> 11878.553 | C97: =VLOOKUP(A97,'2025'!$B$2:$H$105,7,FALSE)/100 -> 3.077 | D97: =VLOOKUP(A97,$M$3:$O$268,3,FALSE) -> 6799.5733 | E97: =VLOOKUP(A97,'2015'!$B$2:$H$122,7,FALSE)/100 -> 2.775 | I97: Guyana | J97: GUY | K97: 80155.039 | M97: Guyana | N97: GUY | O97: 11408.474
A98: Viet Nam | B98: =VLOOKUP(A98,$I$3:$K$268,3,FALSE) -> 16385.507 | C98: =VLOOKUP(A98,'2025'!$B$2:$H$105,7,FALSE)/100 -> #N/A | D98: =VLOOKUP(A98,$M$3:$O$268,3,FALSE) -> 7671.582 | E98: =VLOOKUP(A98,'2015'!$B$2:$H$122,7,FALSE)/100 -> #N/A | I98: High income | J98: HIC | K98: 67051.678 | M98: High income | N98: HIC | O98: 43078.305
I99: Hong Kong SAR, China | J99: HKG | K99: 75195.987 | M99: Hong Kong SAR, China | N99: HKG | O99: 56043.043
I100: Honduras | J100: HND | K100: 7486.0187 | M100: Honduras | N100: HND | O100: 4845.5957
I101: Heavily indebted poor countries (HIPC) | J101: HPC | K101: 3611.7626 | M101: Heavily indebted poor countries (HIPC) | N101: HPC | O101: 2407.8225
I102: Croatia | J102: HRV | K102: 49645.746 | M102: Croatia | N102: HRV | O102: 22187.177
I103: Haiti | J103: HTI | K103: 3193.6714 | M103: Haiti | N103: HTI | O103: 3025.8346
I104: Hungary | J104: HUN | K104: 48552.471 | M104: Hungary | N104: HUN | O104: 26937.732
I105: IBRD only | J105: IBD | K105: 21126.946 | M105: IBRD only | N105: IBD | O105: 11684.143
I106: IDA & IBRD total | J106: IBT | K106: 16790.149 | M106: IDA & IBRD total | N106: IBT | O106: 9673.0234
I107: IDA total | J107: IDA | K107: 5710.1446 | M107: IDA total | N107: IDA | O107: 3818.711
I108: IDA blend | J108: IDB | K108: 7631.6229 | M108: IDA blend | N108: IDB | O108: 5466.8623
...

Sheet Sheet4
B1: 2025 | C1: 2025 | D1: 2015 | E1: 2015
A2: Country | B2: GDP per capita | C2: Mortgage as a percentage of Income | D2: GDP per capita | E2: Mortgage as a percentage of Income | F2: GDP growth | G2: Mortgage growth | H2: Countries that have doubled GDP and experienced house affordability | I2: Countries that doubled GDP but experience bubble in housing
A3: Romania | B3: 49558.669 | C3: 0.952 | D3: 20201.858 | E3: 1.09 | F3: =B3/D3-1 -> 1.4531738 | G3: =C3-E3 -> -0.138 | H3: 1
A4: Bulgaria | B4: 42224.445 | C4: 0.692 | D4: 17652.947 | E4: 0.93 | F4: =B4/D4-1 -> 1.3919204 | G4: =C4-E4 -> -0.238 | H4: 1
A5: Albania | B5: 27146.381 | C5: 1.278 | D5: 11571.707 | E5: 1.384 | F5: =B5/D5-1 -> 1.3459272 | G5: =C5-E5 -> -0.106 | H5: 1
A6: Montenegro | B6: 34806.948 | C6: 1.097 | D6: 15033.061 | E6: 1.702 | F6: =B6/D6-1 -> 1.31536 | G6: =C6-E6 -> -0.605 | H6: 1
A7: Georgia | B7: 28285.073 | C7: 1.654 | D7: 12269.653 | E7: 2.086 | F7: =B7/D7-1 -> 1.3052872 | G7: =C7-E7 -> -0.432 | H7: 1
A8: Bangladesh | B8: 9646.7698 | C8: 1.471 | D8: 4212.2358 | E8: 1.94 | F8: =B8/D8-1 -> 1.290178 | G8: =C8-E8 -> -0.469 | H8: 1
A9: Serbia | B9: 32781.014 | C9: 1.465 | D9: 14523.539 | E9: 1.553 | F9: =B9/D9-1 -> 1.2570955 | G9: =C9-E9 -> -0.088 | H9: 1
A10: Croatia | B10: 49645.746 | C10: 0.958 | D10: 22187.177 | E10: 1.1 | F10: =B10/D10-1 -> 1.2375873 | G10: =C10-E10 -> -0.142 | H10: 1
A11: Cyprus | B11: 62312.074 | C11: 0.612 | D11: 29315.725 | E11: 0.64 | F11: =B11/D11-1 -> 1.1255512 | G11: =C11-E11 -> -0.028 | H11: 1
A12: Bosnia And Herzegovina | B12: 23345.497 | C12: 0.997 | D12: 11066.154 | E12: 1.237 | F12: =B12/D12-1 -> 1.1096306 | G12: =C12-E12 -> -0.24 | H12: 1
A13: India | B13: 11159.986 | C13: 1.177 | D13: 5425.036 | E13: 1.244 | F13: =B13/D13-1 -> 1.0571266 | G13: =C13-E13 -> -0.067 | H13: 1
A14: Moldova | B14: 18614.988 | C14: 1.495 | D14: 9197.6184 | E14: 2.673 | F14: =B14/D14-1 -> 1.0238922 | G14: =C14-E14 -> -1.178 | H14: 1
A15: China | B15: 27104.87 | C15: 2.129 | D15: 13463.333 | E15: 2.306 | F15: =B15/D15-1 -> 1.0132362 | G15: =C15-E15 -> -0.177 | H15: 1
A16: Armenia | B16: 22823.18 | C16: 3.083 | D16: 9756.8408 | E16: 1.974 | F16: =B16/D16-1 -> 1.3391977 | G16: =C16-E16 -> 1.109 | I16: 1
A17: Lithuania | B17: 55285.899 | C17: 0.919 | D17: 26948.592 | E17: 0.875 | F17: =B17/D17-1 -> 1.051532 | G17: =C17-E17 -> 0.044 | I17: 1
A18: Malta | B18: 71017.774 | C18: 0.861 | D18: 35844.479 | E18: 0.498 | F18: =B18/D18-1 -> 0.98127514 | G18: =C18-E18 -> 0.363 | I18: 1
A19: Latvia | B19: 43394.273 | C19: 0.641 | D19: 22543.918 | E19: 0.835 | F19: =B19/D19-1 -> 0.92487715 | G19: =C19-E19 -> -0.194
A20: North Macedonia | B20: 26986.569 | C20: 0.965 | D20: 14045.071 | E20: 1.481 | F20: =B20/D20-1 -> 0.92142627 | G20: =C20-E20 -> -0.516
A21: Poland | B21: 51262.511 | C21: 1.021 | D21: 26988.107 | E21: 0.831 | F21: =B21/D21-1 -> 0.89944818 | G21: =C21-E21 -> 0.19
A22: Ukraine | B22: 18550.463 | C22: 2.533 | D22: 9921.834 | E22: 3.493 | F22: =B22/D22-1 -> 0.86966068 | G22: =C22-E22 -> -0.96
A23: Dominican Republic | B23: 27541.663 | C23: 2.349 | D23: 14804.097 | E23: 1.719 | F23: =B23/D23-1 -> 0.86040809 | G23: =C23-E23 -> 0.63
A24: Slovenia | B24: 57186.371 | C24: 0.94 | D24: 31336.204 | E24: 0.796 | F24: =B24/D24-1 -> 0.82492974 | G24: =C24-E24 -> 0.144
A25: Kazakhstan | B25: 40890.932 | C25: 1.773 | D25: 22484.365 | E25: 1.867 | F25: =B25/D25-1 -> 0.81863849 | G25: =C25-E25 -> -0.094
A26: Hungary | B26: 48552.471 | C26: 1.271 | D26: 26937.732 | E26: 0.84 | F26: =B26/D26-1 -> 0.80239638 | G26: =C26-E26 -> 0.431
A27: Costa Rica | B27: 31106.764 | C27: 1.225 | D27: 17525.14 | E27: 0.843 | F27: =B27/D27-1 -> 0.77497946 | G27: =C27-E27 -> 0.382
A28: Uzbekistan | B28: 11878.553 | C28: 3.077 | D28: 6799.5733 | E28: 2.775 | F28: =B28/D28-1 -> 0.74695562 | G28: =C28-E28 -> 0.302
A29: Portugal | B29: 51679.888 | C29: 1.155 | D29: 29608.007 | E29: 0.619 | F29: =B29/D29-1 -> 0.74547 | G29: =C29-E29 -> 0.536
A30: Iceland | B30: 84256.845 | C30: 0.746 | D30: 49201.064 | E30: 0.527 | F30: =B30/D30-1 -> 0.71250047 | G30: =C30-E30 -> 0.219
... A77: United Arab Emirates | B77: 79228.739 | C77: 0.539 | D77: 73986.064 | E77: 0.499 | F77: =B77/D77-1 -> 0.070860307 | G77: =C77-E77 -> 0.04
