Workbook

Sheet 2025
A1: Rank | B1: Country | C1: Price To Income Ratio | D1: Gross Rental Yield City Centre | E1: Gross Rental Yield Outside of Centre | F1: Price To Rent Ratio City Centre | G1: Price To Rent Ratio Outside Of City Centre | H1: Mortgage As A Percentage Of Income | I1: Affordability Index
A2: 1 | B2: Syria | C2: 115.1 | D2: 2.4 | E2: 3.8 | F2: 41.1 | G2: 26.3 | H2: 1746.8 | I2: 0.1
A3: 2 | B3: Cuba | C3: 48 | D3: 24 | E3: 28.3 | F3: 4.2 | G3: 3.5 | H3: 530.3 | I3: 0.2
A4: 3 | B4: Ethiopia | C4: 47.1 | D4: 6 | E4: 5.4 | F4: 16.7 | G4: 18.6 | H4: 762.3 | I4: 0.1
A5: 4 | B5: Cameroon | C5: 46.6 | D5: 9.2 | E5: 11.4 | F5: 10.8 | G5: 8.8 | H5: 907.8 | I5: 0.1
A6: 5 | B6: Sri Lanka | C6: 34.2 | D6: 3.7 | E6: 2.7 | F6: 26.7 | G6: 36.5 | H6: 603.5 | I6: 0.2
A7: 6 | B7: Nepal | C7: 32.1 | D7: 1.7 | E7: 1.8 | F7: 60 | G7: 56.3 | H7: 447.4 | I7: 0.2
A8: 7 | B8: Hong Kong (China) | C8: 29.1 | D8: 1.9 | E8: 2.2 | F8: 52.2 | G8: 44.7 | H8: 211.2 | I8: 0.5
A9: 8 | B9: China | C9: 28.5 | D9: 1.6 | E9: 1.9 | F9: 62.5 | G9: 51.8 | H9: 212.9 | I9: 0.5
A10: 9 | B10: Vietnam | C10: 25.8 | D10: 3 | E10: 3.6 | F10: 33.3 | G10: 28 | H10: 296.2 | I10: 0.3
A11: 10 | B11: Thailand | C11: 25.2 | D11: 2.9 | E11: 3.2 | F11: 34 | G11: 31.5 | H11: 213.4 | I11: 0.5
A12: 11 | B12: Singapore | C12: 23.2 | D12: 2.9 | E12: 3.1 | F12: 34.2 | G12: 32.4 | H12: 158.4 | I12: 0.6
A13: 12 | B13: Philippines | C13: 22.2 | D13: 3 | E13: 3.5 | F13: 33.1 | G13: 28.5 | H13: 211.5 | I13: 0.5
... A105: 104 | B105: Saudi Arabia | C105: 3.1 | D105: 6.3 | E105: 7.4 | F105: 15.9 | G105: 13.5 | H105: 24 | I105: 4.2

Sheet 2015
A1: Rank | B1: Country | C1: Price To Income Ratio | D1: Gross Rental Yield City Centre | E1: Gross Rental Yield Outside of Centre | F1: Price To Rent Ratio City Centre | G1: Price To Rent Ratio Outside Of City Centre | H1: Mortgage As A Percentage Of Income | I1: Affordability Index
A2: 1 | B2: Uganda | C2: 31.1 | D2: 1.9 | E2: 10 | F2: 53.7 | G2: 10 | H2: 649.4 | I2: 0.2
A3: 2 | B3: Syria | C3: 30.5 | D3: 3.9 | E3: 3.1 | F3: 25.3 | G3: 31.8 | H3: 283.7 | I3: 0.4
A4: 3 | B4: Hong Kong | C4: 30.1 | D4: 2.7 | E4: 2.8 | F4: 37.5 | G4: 36.1 | H4: 193 | I4: 0.5
A5: 4 | B5: Myanmar | C5: 26.8 | D5: 8.5 | E5: 2.9 | F5: 11.8 | G5: 33.9 | H5: 318 | I5: 0.3
A6: 5 | B6: Ghana | C6: 26.6 | D6: 10.8 | E6: 13.4 | F6: 9.3 | G6: 7.4 | H6: 670.4 | I6: 0.1
A7: 6 | B7: China | C7: 26.4 | D7: 2.8 | E7: 3 | F7: 35.9 | G7: 33.3 | H7: 230.6 | I7: 0.4
A8: 7 | B8: El Salvador | C8: 25.4 | D8: 5.3 | E8: 1.7 | F8: 18.9 | G8: 60.3 | H8: 336.1 | I8: 0.3
A9: 8 | B9: Taiwan | C9: 25 | D9: 1.4 | E9: 1.8 | F9: 71.4 | G9: 55.5 | H9: 152.3 | I9: 0.7
A10: 9 | B10: Vietnam | C10: 23.9 | D10: 5.2 | E10: 7.6 | F10: 19.3 | G10: 13.1 | H10: 285.6 | I10: 0.4
A11: 10 | B11: Venezuela | C11: 22.2 | D11: 12.5 | E11: 9.3 | F11: 8 | G11: 10.8 | H11: 333.4 | I11: 0.3
A12: 11 | B12: Mauritius | C12: 22.1 | D12: 2.2 | E12: 2.4 | F12: 45.3 | G12: 41.5 | H12: 228.8 | I12: 0.4
A13: 12 | B13: Singapore | C13: 21.4 | D13: 3.4 | E13: 3.9 | F13: 29.2 | G13: 25.7 | H13: 133.3 | I13: 0.8
... A122: 121 | B122: Tanzania | C122: 1.8 | D122: 80.3 | E122: 27.8 | F122: 1.2 | G122: 3.6 | H122: 27.9 | I122: 3.6

Sheet Sheet3
B1: 2025 | C1: 2025 | D1: 2015 | E1: 2015
A2: Country | B2: GDP per capita | C2: Mortgage as a percentage of Income | D2: GDP per capita | E2: Mortgage as a percentage of Income | J2: Country Name | K2: Country Code | L2: 2024 | N2: Country Name | O2: Country Code | P2: 2015
A3: Albania | B3: =VLOOKUP(A3,$J$3:$L$268,3,FALSE) -> 27146.381 | C3: =VLOOKUP(A3,'2025'!$B$2:$H$105,2,FALSE)/100 -> 0.153 | D3: =VLOOKUP(A3,$N$3:$P$268,3,FALSE) -> 11571.707 | E3: =VLOOKUP(A3,'2015'!$B$2:$H$122,2,FALSE)/100 -> 0.146 | F3: =B3/D3-1 -> 1.3459272 | J3: Aruba | K3: ABW | L3: 50649.302 | N3: Aruba | O3: ABW | P3: 35972.86 | R3: Czech Republic | S3: Czechia
A4: Algeria | B4: =VLOOKUP(A4,$J$3:$L$268,3,FALSE) -> 17620.742 | C4: =VLOOKUP(A4,'2025'!$B$2:$H$105,2,FALSE)/100 -> 0.167 | D4: =VLOOKUP(A4,$N$3:$P$268,3,FALSE) -> 13807.352 | E4: =VLOOKUP(A4,'2015'!$B$2:$H$122,2,FALSE)/100 -> 0.209 | J4: Africa Eastern and Southern | K4: AFE | L4: 4635.7882 | N4: Africa Eastern and Southern | O4: AFE | P4: 3539.8155 | R4: Egypt | S4: Egypt, Arab Rep.
A5: Argentina | B5: =VLOOKUP(A5,$J$3:$L$268,3,FALSE) -> 30431.193 | C5: =VLOOKUP(A5,'2025'!$B$2:$H$105,2,FALSE)/100 -> 0.177 | D5: =VLOOKUP(A5,$N$3:$P$268,3,FALSE) -> 19899.15 | E5: =VLOOKUP(A5,'2015'!$B$2:$H$122,2,FALSE)/100 -> 0.116 | J5: Afghanistan | K5: AFG | N5: Afghanistan | O5: AFG | P5: 2284.0758 | R5: Hong Kong (China) | S5: Hong Kong SAR, China
A6: Armenia | B6: =VLOOKUP(A6,$J$3:$L$268,3,FALSE) -> 22823.18 | C6: =VLOOKUP(A6,'2025'!$B$2:$H$105,2,FALSE)/100 -> 0.194 | D6: =VLOOKUP(A6,$N$3:$P$268,3,FALSE) -> 9756.8408 | E6: =VLOOKUP(A6,'2015'!$B$2:$H$122,2,FALSE)/100 -> 0.134 | J6: Africa Western and Central | K6: AFW | L6: 6815.991 | N6: Africa Western and Central | O6: AFW | P6: 5056.7394 | R6: Iran | S6: Iran, Islamic Rep.
A7: Australia | B7: =VLOOKUP(A7,$J$3:$L$268,3,FALSE) -> 72111.184 | C7: =VLOOKUP(A7,'2025'!$B$2:$H$105,2,FALSE)/100 -> 0.081 | D7: =VLOOKUP(A7,$N$3:$P$268,3,FALSE) -> 46464.587 | E7: =VLOOKUP(A7,'2015'!$B$2:$H$122,2,FALSE)/100 -> 0.071 | J7: Angola | K7: AGO | L7: 10118.609 | N7: Angola | O7: AGO | P7: 8067.4858 | R7: Kosovo (Disputed Territory)
A8: Austria | B8: =VLOOKUP(A8,$J$3:$L$268,3,FALSE) -> 73911.44 | C8: =VLOOKUP(A8,'2025'!$B$2:$H$105,2,FALSE)/100 -> 0.115 | D8: =VLOOKUP(A8,$N$3:$P$268,3,FALSE) -> 49549.316 | E8: =VLOOKUP(A8,'2015'!$B$2:$H$122,2,FALSE)/100 -> 0.096 | J8: Albania | K8: ALB | L8: 27146.381 | N8: Albania | O8: ALB | P8: 11571.707 | R8: Kyrgyzstan | S8: Kyrgyz Republic
A9: Azerbaijan | B9: =VLOOKUP(A9,$J$3:$L$268,3,FALSE) -> 25088.999 | C9: =VLOOKUP(A9,'2025'!$B$2:$H$105,2,FALSE)/100 -> 0.156 | D9: =VLOOKUP(A9,$N$3:$P$268,3,FALSE) -> 15075.273 | E9: =VLOOKUP(A9,'2015'!$B$2:$H$122,2,FALSE)/100 -> 0.162 | J9: Andorra | K9: AND | L9: 74939.475 | N9: Andorra | O9: AND | P9: 50733.239 | R9: Palestine
A10: Bangladesh | B10: =VLOOKUP(A10,$J$3:$L$268,3,FALSE) -> 9646.7698 | C10: =VLOOKUP(A10,'2025'!$B$2:$H$105,2,FALSE)/100 -> 0.128 | D10: =VLOOKUP(A10,$N$3:$P$268,3,FALSE) -> 4212.2358 | E10: =VLOOKUP(A10,'2015'!$B$2:$H$122,2,FALSE)/100 -> 0.109 | J10: Arab World | K10: ARB | L10: 18870.315 | N10: Arab World | O10: ARB | P10: 14332.866 | R10: Puerto Rico
A11: Belarus | B11: =VLOOKUP(A11,$J$3:$L$268,3,FALSE) -> 33010.331 | C11: =VLOOKUP(A11,'2025'!$B$2:$H$105,2,FALSE)/100 -> 0.128 | D11: =VLOOKUP(A11,$N$3:$P$268,3,FALSE) -> 18133.531 | E11: =VLOOKUP(A11,'2015'!$B$2:$H$122,2,FALSE)/100 -> 0.164 | J11: United Arab Emirates | K11: ARE | L11: 79228.739 | N11: United Arab Emirates | O11: ARE | P11: 73986.064 | R11: Russia | S11: Russian Federation
A12: Belgium | B12: =VLOOKUP(A12,$J$3:$L$268,3,FALSE) -> 73514.483 | C12: =VLOOKUP(A12,'2025'!$B$2:$H$105,2,FALSE)/100 -> 0.068 | D12: =VLOOKUP(A12,$N$3:$P$268,3,FALSE) -> 46071.915 | E12: =VLOOKUP(A12,'2015'!$B$2:$H$122,2,FALSE)/100 -> 0.065 | J12: Argentina | K12: ARG | L12: 30431.193 | N12: Argentina | O12: ARG | P12: 19899.15 | R12: Slovakia | S12: Slovak Republic
A13: Bolivia | B13: =VLOOKUP(A13,$J$3:$L$268,3,FALSE) -> 12877.635 | C13: =VLOOKUP(A13,'2025'!$B$2:$H$105,2,FALSE)/100 -> 0.12 | D13: =VLOOKUP(A13,$N$3:$P$268,3,FALSE) -> 8757.3178 | E13: =VLOOKUP(A13,'2015'!$B$2:$H$122,2,FALSE)/100 -> 0.103 | J13: Armenia | K13: ARM | L13: 22823.18 | N13: Armenia | O13: ARM | P13: 9756.8408 | R13: South Korea | S13: Korea, Rep.
A14: Bosnia And Herzegovina | B14: =VLOOKUP(A14,$J$3:$L$268,3,FALSE) -> 23345.497 | C14: =VLOOKUP(A14,'2025'!$B$2:$H$105,2,FALSE)/100 -> 0.132 | D14: =VLOOKUP(A14,$N$3:$P$268,3,FALSE) -> 11066.154 | E14: =VLOOKUP(A14,'2015'!$B$2:$H$122,2,FALSE)/100 -> 0.125 | J14: American Samoa | K14: ASM | N14: American Samoa | O14: ASM | R14: Taiwan
A15: Brazil | B15: =VLOOKUP(A15,$J$3:$L$268,3,FALSE) -> 22338.477 | C15: =VLOOKUP(A15,'2025'!$B$2:$H$105,2,FALSE)/100 -> 0.152 | D15: =VLOOKUP(A15,$N$3:$P$268,3,FALSE) -> 14821.438 | E15: =VLOOKUP(A15,'2015'!$B$2:$H$122,2,FALSE)/100 -> 0.167 | J15: Antigua and Barbuda | K15: ATG | L15: 33386.192 | N15: Antigua and Barbuda | O15: ATG | P15: 20985.439 | R15: Turkey | S15: Turkiye
A16: Bulgaria | B16: =VLOOKUP(A16,$J$3:$L$268,3,FALSE) -> 42224.445 | C16: =VLOOKUP(A16,'2025'!$B$2:$H$105,2,FALSE)/100 -> 0.093 | D16: =VLOOKUP(A16,$N$3:$P$268,3,FALSE) -> 17652.947 | E16: =VLOOKUP(A16,'2015'!$B$2:$H$122,2,FALSE)/100 -> 0.094 | J16: Australia | K16: AUS | L16: 72111.184 | N16: Australia | O16: AUS | P16: 46464.587 | R16: Venezuela | S16: Venezuela, RB
A17: Cameroon | B17: =VLOOKUP(A17,$J$3:$L$268,3,FALSE) -> 5588.9865 | C17: =VLOOKUP(A17,'2025'!$B$2:$H$105,2,FALSE)/100 -> 0.466 | D17: =VLOOKUP(A17,$N$3:$P$268,3,FALSE) -> 3497.6607 | E17: =VLOOKUP(A17,'2015'!$B$2:$H$122,2,FALSE)/100 -> #N/A | J17: Austria | K17: AUT | L17: 73911.44 | N17: Austria | O17: AUT | P17: 49549.316 | R17: Vietnam | S17: Viet Nam
A18: Canada | B18: =VLOOKUP(A18,$J$3:$L$268,3,FALSE) -> 64610.38 | C18: =VLOOKUP(A18,'2025'!$B$2:$H$105,2,FALSE)/100 -> 0.102 | D18: =VLOOKUP(A18,$N$3:$P$268,3,FALSE) -> 44668.091 | E18: =VLOOKUP(A18,'2015'!$B$2:$H$122,2,FALSE)/100 -> 0.055 | J18: Azerbaijan | K18: AZE | L18: 25088.999 | N18: Azerbaijan | O18: AZE | P18: 15075.273
A19: Chile | B19: =VLOOKUP(A19,$J$3:$L$268,3,FALSE) -> 36181.157 | C19: =VLOOKUP(A19,'2025'!$B$2:$H$105,2,FALSE)/100 -> 0.156 | D19: =VLOOKUP(A19,$N$3:$P$268,3,FALSE) -> 22468.313 | E19: =VLOOKUP(A19,'2015'!$B$2:$H$122,2,FALSE)/100 -> 0.108 | J19: Burundi | K19: BDI | L19: 1194.9468 | N19: Burundi | O19: BDI | P19: 722.0329
A20: China | B20: =VLOOKUP(A20,$J$3:$L$268,3,FALSE) -> 27104.87 | C20: =VLOOKUP(A20,'2025'!$B$2:$H$105,2,FALSE)/100 -> 0.285 | D20: =VLOOKUP(A20,$N$3:$P$268,3,FALSE) -> 13463.333 | E20: =VLOOKUP(A20,'2015'!$B$2:$H$122,2,FALSE)/100 -> 0.264 | J20: Belgium | K20: BEL | L20: 73514.483 | N20: Belgium | O20: BEL | P20: 46071.915
A21: Colombia | B21: =VLOOKUP(A21,$J$3:$L$268,3,FALSE) -> 22349.436 | C21: =VLOOKUP(A21,'2025'!$B$2:$H$105,2,FALSE)/100 -> 0.181 | D21: =VLOOKUP(A21,$N$3:$P$268,3,FALSE) -> 13332.056 | E21: =VLOOKUP(A21,'2015'!$B$2:$H$122,2,FALSE)/100 -> 0.144 | J21: Benin | K21: BEN | L21: 4434.5642 | N21: Benin | O21: BEN | P21: 2725.3372
A22: Costa Rica | B22: =VLOOKUP(A22,$J$3:$L$268,3,FALSE) -> 31106.764 | C22: =VLOOKUP(A22,'2025'!$B$2:$H$105,2,FALSE)/100 -> 0.103 | D22: =VLOOKUP(A22,$N$3:$P$268,3,FALSE) -> 17525.14 | E22: =VLOOKUP(A22,'2015'!$B$2:$H$122,2,FALSE)/100 -> 0.057 | J22: Burkina Faso | K22: BFA | L22: 2895.8915 | N22: Burkina Faso | O22: BFA | P22: 1691.5794
A23: Croatia | B23: =VLOOKUP(A23,$J$3:$L$268,3,FALSE) -> 49645.746 | C23: =VLOOKUP(A23,'2025'!$B$2:$H$105,2,FALSE)/100 -> 0.128 | D23: =VLOOKUP(A23,$N$3:$P$268,3,FALSE) -> 22187.177 | E23: =VLOOKUP(A23,'2015'!$B$2:$H$122,2,FALSE)/100 -> 0.125 | J23: Bangladesh | K23: BGD | L23: 9646.7698 | N23: Bangladesh | O23: BGD | P23: 4212.2358
A24: Cyprus | B24: =VLOOKUP(A24,$J$3:$L$268,3,FALSE) -> 62312.074 | C24: =VLOOKUP(A24,'2025'!$B$2:$H$105,2,FALSE)/100 -> 0.082 | D24: =VLOOKUP(A24,$N$3:$P$268,3,FALSE) -> 29315.725 | E24: =VLOOKUP(A24,'2015'!$B$2:$H$122,2,FALSE)/100 -> 0.074 | J24: Bulgaria | K24: BGR | L24: 42224.445 | N24: Bulgaria | O24: BGR | P24: 17652.947
A25: Czechia | B25: =VLOOKUP(A25,$J$3:$L$268,3,FALSE) -> 57285.424 | C25: =VLOOKUP(A25,'2025'!$B$2:$H$105,2,FALSE)/100 -> #N/A | D25: =VLOOKUP(A25,$N$3:$P$268,3,FALSE) -> 34093.028 | E25: =VLOOKUP(A25,'2015'!$B$2:$H$122,2,FALSE)/100 -> #N/A | J25: Bahrain | K25: BHR | L25: 66941.243 | N25: Bahrain | O25: BHR | P25: 48034.247
A26: Denmark | B26: =VLOOKUP(A26,$J$3:$L$268,3,FALSE) -> 81878.235 | C26: =VLOOKUP(A26,'2025'!$B$2:$H$105,2,FALSE)/100 -> 0.065 | D26: =VLOOKUP(A26,$N$3:$P$268,3,FALSE) -> 48897.21 | E26: =VLOOKUP(A26,'2015'!$B$2:$H$122,2,FALSE)/100 -> 0.05 | J26: Bahamas, The | K26: BHS | L26: 41197.934 | N26: Bahamas, The | O26: BHS | P26: 32137.578
A27: Dominican Republic | B27: =VLOOKUP(A27,$J$3:$L$268,3,FALSE) -> 27541.663 | C27: =VLOOKUP(A27,'2025'!$B$2:$H$105,2,FALSE)/100 -> 0.165 | D27: =VLOOKUP(A27,$N$3:$P$268,3,FALSE) -> 14804.097 | E27: =VLOOKUP(A27,'2015'!$B$2:$H$122,2,FALSE)/100 -> 0.115 | J27: Bosnia and Herzegovina | K27: BIH | L27: 23345.497 | N27: Bosnia and Herzegovina | O27: BIH | P27: 11066.154
A28: Ecuador | B28: =VLOOKUP(A28,$J$3:$L$268,3,FALSE) -> 15840.267 | C28: =VLOOKUP(A28,'2025'!$B$2:$H$105,2,FALSE)/100 -> 0.119 | D28: =VLOOKUP(A28,$N$3:$P$268,3,FALSE) -> 10877.751 | E28: =VLOOKUP(A28,'2015'!$B$2:$H$122,2,FALSE)/100 -> 0.147 | J28: Belarus | K28: BLR | L28: 33010.331 | N28: Belarus | O28: BLR | P28: 18133.531
A29: Egypt, Arab Rep. | B29: =VLOOKUP(A29,$J$3:$L$268,3,FALSE) -> 19094.145 | C29: =VLOOKUP(A29,'2025'!$B$2:$H$105,2,FALSE)/100 -> #N/A | D29: =VLOOKUP(A29,$N$3:$P$268,3,FALSE) -> 10903.337 | E29: =VLOOKUP(A29,'2015'!$B$2:$H$122,2,FALSE)/100 -> #N/A | J29: Belize | K29: BLZ | L29: 14346.519 | N29: Belize | O29: BLZ | P29: 9538.3869
... A34: France | B34: =VLOOKUP(A34,$J$3:$L$268,3,FALSE) -> 62556.918 | C34: =VLOOKUP(A34,'2025'!$B$2:$H$105,2,FALSE)/100 -> 0.103 | D34: =VLOOKUP(A34,$N$3:$P$268,3,FALSE) -> 40905.177 | E34: =VLOOKUP(A34,'2015'!$B$2:$H$122,2,FALSE)/100 -> 0.097 | J34: Brunei Darussalam | K34: BRN | L34: 89879.361 | N34: Brunei Darussalam | O34: BRN | P34: 62707.826
A35: Georgia | B35: =VLOOKUP(A35,$J$3:$L$268,3,FALSE) -> 28285.073 | C35: =VLOOKUP(A35,'2025'!$B$2:$H$105,2,FALSE)/100 -> 0.127 | D35: =VLOOKUP(A35,$N$3:$P$268,3,FALSE) -> 12269.653 | E35: =VLOOKUP(A35,'2015'!$B$2:$H$122,2,FALSE)/100 -> 0.152 | J35: Bhutan | K35: BTN | N35: Bhutan | O35: BTN | P35: 10213.814
A36: Germany | B36: =VLOOKUP(A36,$J$3:$L$268,3,FALSE) -> 73551.935 | C36: =VLOOKUP(A36,'2025'!$B$2:$H$105,2,FALSE)/100 -> 0.089 | D36: =VLOOKUP(A36,$N$3:$P$268,3,FALSE) -> 48545.401 | E36: =VLOOKUP(A36,'2015'!$B$2:$H$122,2,FALSE)/100 -> 0.066 | J36: Botswana | K36: BWA | L36: 20538.132 | N36: Botswana | O36: BWA | P36: 14143.694
A37: Greece | B37: =VLOOKUP(A37,$J$3:$L$268,3,FALSE) -> 44327.21 | C37: =VLOOKUP(A37,'2025'!$B$2:$H$105,2,FALSE)/100 -> 0.13 | D37: =VLOOKUP(A37,$N$3:$P$268,3,FALSE) -> 26607.726 | E37: =VLOOKUP(A37,'2015'!$B$2:$H$122,2,FALSE)/100 -> 0.097 | J37: Central African Republic | K37: CAF | L37: 1263.1023 | N37: Central African Republic | O37: CAF | P37: 768.87089
A38: Hong Kong SAR, China | B38: =VLOOKUP(A38,$J$3:$L$268,3,FALSE) -> 75195.987 | C38: =VLOOKUP(A38,'2025'!$B$2:$H$105,2,FALSE)/100 -> #N/A | D38: =VLOOKUP(A38,$N$3:$P$268,3,FALSE) -> 56043.043 | E38: =VLOOKUP(A38,'2015'!$B$2:$H$122,2,FALSE)/100 -> #N/A | J38: Canada | K38: CAN | L38: 64610.38 | N38: Canada | O38: CAN | P38: 44668.091
A39: Hungary | B39: =VLOOKUP(A39,$J$3:$L$268,3,FALSE) -> 48552.471 | C39: =VLOOKUP(A39,'2025'!$B$2:$H$105,2,FALSE)/100 -> 0.13 | D39: =VLOOKUP(A39,$N$3:$P$268,3,FALSE) -> 26937.732 | E39: =VLOOKUP(A39,'2015'!$B$2:$H$122,2,FALSE)/100 -> 0.086 | J39: Central Europe and the Baltics | K39: CEB | L39: 50599.212 | N39: Central Europe and the Baltics | O39: CEB | P39: 25780.239
A40: Iceland | B40: =VLOOKUP(A40,$J$3:$L$268,3,FALSE) -> 84256.845 | C40: =VLOOKUP(A40,'2025'!$B$2:$H$105,2,FALSE)/100 -> 0.067 | D40: =VLOOKUP(A40,$N$3:$P$268,3,FALSE) -> 49201.064 | E40: =VLOOKUP(A40,'2015'!$B$2:$H$122,2,FALSE)/100 -> 0.056 | J40: Switzerland | K40: CHE | L40: 96497.695 | N40: Switzerland | O40: CHE | P40: 65265.046
A41: India | B41: =VLOOKUP(A41,$J$3:$L$268,3,FALSE) -> 11159.986 | C41: =VLOOKUP(A41,'2025'!$B$2:$H$105,2,FALSE)/100 -> 0.109 | D41: =VLOOKUP(A41,$N$3:$P$268,3,FALSE) -> 5425.036 | E41: =VLOOKUP(A41,'2015'!$B$2:$H$122,2,FALSE)/100 -> 0.101 | J41: Channel Islands | K41: CHI | N41: Channel Islands | O41: CHI
A42: Indonesia | B42: =VLOOKUP(A42,$J$3:$L$268,3,FALSE) -> 16448.276 | C42: =VLOOKUP(A42,'2025'!$B$2:$H$105,2,FALSE)/100 -> 0.149 | D42: =VLOOKUP(A42,$N$3:$P$268,3,FALSE) -> 10027.537 | E42: =VLOOKUP(A42,'2015'!$B$2:$H$122,2,FALSE)/100 -> 0.189 | J42: Chile | K42: CHL | L42: 36181.157 | N42: Chile | O42: CHL | P42: 22468.313
A43: Iran, Islamic Rep. | B43: =VLOOKUP(A43,$J$3:$L$268,3,FALSE) -> 19873.886 | C43: =VLOOKUP(A43,'2025'!$B$2:$H$105,2,FALSE)/100 -> #N/A | D43: =VLOOKUP(A43,$N$3:$P$268,3,FALSE) -> 14273.55 | E43: =VLOOKUP(A43,'2015'!$B$2:$H$122,2,FALSE)/100 -> #N/A | J43: China | K43: CHN | L43: 27104.87 | N43: China | O43: CHN | P43: 13463.333
A44: Iraq | B44: =VLOOKUP(A44,$J$3:$L$268,3,FALSE) -> 14464.319 | C44: =VLOOKUP(A44,'2025'!$B$2:$H$105,2,FALSE)/100 -> 0.084 | D44: =VLOOKUP(A44,$N$3:$P$268,3,FALSE) -> 9334.466 | E44: =VLOOKUP(A44,'2015'!$B$2:$H$122,2,FALSE)/100 -> 0.089 | J44: Cote d'Ivoire | K44: CIV | L44: 7669.232 | N44: Cote d'Ivoire | O44: CIV | P44: 4403.643
A45: Ireland | B45: =VLOOKUP(A45,$J$3:$L$268,3,FALSE) -> 133437.47 | C45: =VLOOKUP(A45,'2025'!$B$2:$H$105,2,FALSE)/100 -> 0.067 | D45: =VLOOKUP(A45,$N$3:$P$268,3,FALSE) -> 71588.266 | E45: =VLOOKUP(A45,'2015'!$B$2:$H$122,2,FALSE)/100 -> 0.061 | J45: Cameroon | K45: CMR | L45: 5588.9865 | N45: Cameroon | O45: CMR | P45: 3497.6607
A46: Israel | B46: =VLOOKUP(A46,$J$3:$L$268,3,FALSE) -> 57235.776 | C46: =VLOOKUP(A46,'2025'!$B$2:$H$105,2,FALSE)/100 -> 0.137 | D46: =VLOOKUP(A46,$N$3:$P$268,3,FALSE) -> 35870.793 | E46: =VLOOKUP(A46,'2015'!$B$2:$H$122,2,FALSE)/100 -> 0.107 | J46: Congo, Dem. Rep. | K46: COD | L46: 1821.0487 | N46: Congo, Dem. Rep. | O46: COD | P46: 910.39313
A47: Italy | B47: =VLOOKUP(A47,$J$3:$L$268,3,FALSE) -> 62014.268 | C47: =VLOOKUP(A47,'2025'!$B$2:$H$105,2,FALSE)/100 -> 0.095 | D47: =VLOOKUP(A47,$N$3:$P$268,3,FALSE) -> 37384.38 | E47: =VLOOKUP(A47,'2015'!$B$2:$H$122,2,FALSE)/100 -> 0.117 | J47: Congo, Rep. | K47: COG | L47: 7026.3622 | N47: Congo, Rep. | O47: COG | P47: 4715.1343
A48: Japan | B48: =VLOOKUP(A48,$J$3:$L$268,3,FALSE) -> 52039.172 | C48: =VLOOKUP(A48,'2025'!$B$2:$H$105,2,FALSE)/100 -> 0.122 | D48: =VLOOKUP(A48,$N$3:$P$268,3,FALSE) -> 40898.807 | E48: =VLOOKUP(A48,'2015'!$B$2:$H$122,2,FALSE)/100 -> 0.092 | J48: Colombia | K48: COL | L48: 22349.436 | N48: Colombia | O48: COL | P48: 13332.056
A49: Jordan | B49: =VLOOKUP(A49,$J$3:$L$268,3,FALSE) -> 10821.491 | C49: =VLOOKUP(A49,'2025'!$B$2:$H$105,2,FALSE)/100 -> 0.07 | D49: =VLOOKUP(A49,$N$3:$P$268,3,FALSE) -> 8967.08 | E49: =VLOOKUP(A49,'2015'!$B$2:$H$122,2,FALSE)/100 -> 0.086 | J49: Comoros | K49: COM | L49: 3958.5323 | N49: Comoros | O49: COM | P49: 2949.4734
A50: Kazakhstan | B50: =VLOOKUP(A50,$J$3:$L$268,3,FALSE) -> 40890.932 | C50: =VLOOKUP(A50,'2025'!$B$2:$H$105,2,FALSE)/100 -> 0.099 | D50: =VLOOKUP(A50,$N$3:$P$268,3,FALSE) -> 22484.365 | E50: =VLOOKUP(A50,'2015'!$B$2:$H$122,2,FALSE)/100 -> 0.127 | J50: Cabo Verde | K50: CPV | L50: 11195.121 | N50: Cabo Verde | O50: CPV | P50: 6773.4868
A51: Korea, Rep. | B51: =VLOOKUP(A51,$J$3:$L$268,3,FALSE) -> 61051.349 | C51: =VLOOKUP(A51,'2025'!$B$2:$H$105,2,FALSE)/100 -> #N/A | D51: =VLOOKUP(A51,$N$3:$P$268,3,FALSE) -> 39794.196 | E51: =VLOOKUP(A51,'2015'!$B$2:$H$122,2,FALSE)/100 -> #N/A | J51: Costa Rica | K51: CRI | L51: 31106.764 | N51: Costa Rica | O51: CRI | P51: 17525.14
A52: Kuwait | B52: =VLOOKUP(A52,$J$3:$L$268,3,FALSE) -> 52443.597 | C52: =VLOOKUP(A52,'2025'!$B$2:$H$105,2,FALSE)/100 -> 0.073 | D52: =VLOOKUP(A52,$N$3:$P$268,3,FALSE) -> 45267.309 | E52: =VLOOKUP(A52,'2015'!$B$2:$H$122,2,FALSE)/100 -> 0.061 | J52: Caribbean small states | K52: CSS | L52: 38624.061 | N52: Caribbean small states | O52: CSS | P52: 20632.338
A53: Kyrgyz Republic | B53: =VLOOKUP(A53,$J$3:$L$268,3,FALSE) -> 8012.4546 | C53: =VLOOKUP(A53,'2025'!$B$2:$H$105,2,FALSE)/100 -> #N/A | D53: =VLOOKUP(A53,$N$3:$P$268,3,FALSE) -> 4153.3767 | E53: =VLOOKUP(A53,'2015'!$B$2:$H$122,2,FALSE)/100 -> #N/A | J53: Cuba | K53: CUB | N53: Cuba | O53: CUB
A54: Latvia | B54: =VLOOKUP(A54,$J$3:$L$268,3,FALSE) -> 43394.273 | C54: =VLOOKUP(A54,'2025'!$B$2:$H$105,2,FALSE)/100 -> 0.086 | D54: =VLOOKUP(A54,$N$3:$P$268,3,FALSE) -> 22543.918 | E54: =VLOOKUP(A54,'2015'!$B$2:$H$122,2,FALSE)/100 -> 0.122 | J54: Curacao | K54: CUW | L54: 32693.294 | N54: Curacao | O54: CUW | P54: 24037.649
A55: Lithuania | B55: =VLOOKUP(A55,$J$3:$L$268,3,FALSE) -> 55285.899 | C55: =VLOOKUP(A55,'2025'!$B$2:$H$105,2,FALSE)/100 -> 0.124 | D55: =VLOOKUP(A55,$N$3:$P$268,3,FALSE) -> 26948.592 | E55: =VLOOKUP(A55,'2015'!$B$2:$H$122,2,FALSE)/100 -> 0.129 | J55: Cayman Islands | K55: CYM | N55: Cayman Islands | O55: CYM | P55: 64009.317
A56: Luxembourg | B56: =VLOOKUP(A56,$J$3:$L$268,3,FALSE) -> 155941.29 | C56: =VLOOKUP(A56,'2025'!$B$2:$H$105,2,FALSE)/100 -> 0.086 | D56: =VLOOKUP(A56,$N$3:$P$268,3,FALSE) -> 107859.69 | E56: =VLOOKUP(A56,'2015'!$B$2:$H$122,2,FALSE)/100 -> 0.083 | J56: Cyprus | K56: CYP | L56: 62312.074 | N56: Cyprus | O56: CYP | P56: 29315.725
A57: Malaysia | B57: =VLOOKUP(A57,$J$3:$L$268,3,FALSE) -> 38779.283 | C57: =VLOOKUP(A57,'2025'!$B$2:$H$105,2,FALSE)/100 -> 0.087 | D57: =VLOOKUP(A57,$N$3:$P$268,3,FALSE) -> 24526.394 | E57: =VLOOKUP(A57,'2015'!$B$2:$H$122,2,FALSE)/100 -> 0.084 | J57: Czechia | K57: CZE | L57: 57285.424 | N57: Czechia | O57: CZE | P57: 34093.028
A58: Malta | B58: =VLOOKUP(A58,$J$3:$L$268,3,FALSE) -> 71017.774 | C58: =VLOOKUP(A58,'2025'!$B$2:$H$105,2,FALSE)/100 -> 0.112 | D58: =VLOOKUP(A58,$N$3:$P$268,3,FALSE) -> 35844.479 | E58: =VLOOKUP(A58,'2015'!$B$2:$H$122,2,FALSE)/100 -> 0.072 | J58: Germany | K58: DEU | L58: 73551.935 | N58: Germany | O58: DEU | P58: 48545.401
A59: Mauritius | B59: =VLOOKUP(A59,$J$3:$L$268,3,FALSE) -> 31839.76 | C59: =VLOOKUP(A59,'2025'!$B$2:$H$105,2,FALSE)/100 -> 0.185 | D59: =VLOOKUP(A59,$N$3:$P$268,3,FALSE) -> 20269.524 | E59: =VLOOKUP(A59,'2015'!$B$2:$H$122,2,FALSE)/100 -> 0.221 | J59: Djibouti | K59: DJI | L59: 7810.2787 | N59: Djibouti | O59: DJI | P59: 4263.9629
A60: Mexico | B60: =VLOOKUP(A60,$J$3:$L$268,3,FALSE) -> 26185.356 | C60: =VLOOKUP(A60,'2025'!$B$2:$H$105,2,FALSE)/100 -> 0.118 | D60: =VLOOKUP(A60,$N$3:$P$268,3,FALSE) -> 19071.444 | E60: =VLOOKUP(A60,'2015'!$B$2:$H$122,2,FALSE)/100 -> 0.063 | J60: Dominica | K60: DMA | L60: 21300.685 | N60: Dominica | O60: DMA | P60: 12092.732
A61: Moldova | B61: =VLOOKUP(A61,$J$3:$L$268,3,FALSE) -> 18614.988 | C61: =VLOOKUP(A61,'2025'!$B$2:$H$105,2,FALSE)/100 -> 0.133 | D61: =VLOOKUP(A61,$N$3:$P$268,3,FALSE) -> 9197.6184 | E61: =VLOOKUP(A61,'2015'!$B$2:$H$122,2,FALSE)/100 -> 0.171 | J61: Denmark | K61: DNK | L61: 81878.235 | N61: Denmark | O61: DNK | P61: 48897.21
A62: Montenegro | B62: =VLOOKUP(A62,$J$3:$L$268,3,FALSE) -> 34806.948 | C62: =VLOOKUP(A62,'2025'!$B$2:$H$105,2,FALSE)/100 -> 0.129 | D62: =VLOOKUP(A62,$N$3:$P$268,3,FALSE) -> 15033.061 | E62: =VLOOKUP(A62,'2015'!$B$2:$H$122,2,FALSE)/100 -> 0.161 | J62: Dominican Republic | K62: DOM | L62: 27541.663 | N62: Dominican Republic | O62: DOM | P62: 14804.097
A63: Morocco | B63: =VLOOKUP(A63,$J$3:$L$268,3,FALSE) -> 10415.124 | C63: =VLOOKUP(A63,'2025'!$B$2:$H$105,2,FALSE)/100 -> 0.134 | D63: =VLOOKUP(A63,$N$3:$P$268,3,FALSE) -> 7799.0923 | E63: =VLOOKUP(A63,'2015'!$B$2:$H$122,2,FALSE)/100 -> 0.161 | J63: Algeria | K63: DZA | L63: 17620.742 | N63: Algeria | O63: DZA | P63: 13807.352
A64: Nepal | B64: =VLOOKUP(A64,$J$3:$L$268,3,FALSE) -> 5736.6213 | C64: =VLOOKUP(A64,'2025'!$B$2:$H$105,2,FALSE)/100 -> 0.321 | D64: =VLOOKUP(A64,$N$3:$P$268,3,FALSE) -> 2957.3056 | E64: =VLOOKUP(A64,'2015'!$B$2:$H$122,2,FALSE)/100 -> 0.197 | J64: East Asia & Pacific (excluding high income) | K64: EAP | L64: 23248.025 | N64: East Asia & Pacific (excluding high income) | O64: EAP | P64: 12146.381
A65: Netherlands | B65: =VLOOKUP(A65,$J$3:$L$268,3,FALSE) -> 86173.629 | C65: =VLOOKUP(A65,'2025'!$B$2:$H$105,2,FALSE)/100 -> 0.077 | D65: =VLOOKUP(A65,$N$3:$P$268,3,FALSE) -> 50956.693 | E65: =VLOOKUP(A65,'2015'!$B$2:$H$122,2,FALSE)/100 -> 0.062 | J65: Early-demographic dividend | K65: EAR | L65: 13995.406 | N65: Early-demographic dividend | O65: EAR | P65: 8319.9135
A66: New Zealand | B66: =VLOOKUP(A66,$J$3:$L$268,3,FALSE) -> 55551.144 | C66: =VLOOKUP(A66,'2025'!$B$2:$H$105,2,FALSE)/100 -> 0.073 | D66: =VLOOKUP(A66,$N$3:$P$268,3,FALSE) -> 37513.296 | E66: =VLOOKUP(A66,'2015'!$B$2:$H$122,2,FALSE)/100 -> 0.058 | J66: East Asia & Pacific | K66: EAS | L66: 27285.211 | N66: East Asia & Pacific | O66: EAS | P66: 15476.317
A67: North Macedonia | B67: =VLOOKUP(A67,$J$3:$L$268,3,FALSE) -> 26986.569 | C67: =VLOOKUP(A67,'2025'!$B$2:$H$105,2,FALSE)/100 -> 0.123 | D67: =VLOOKUP(A67,$N$3:$P$268,3,FALSE) -> 14045.071 | E67: =VLOOKUP(A67,'2015'!$B$2:$H$122,2,FALSE)/100 -> 0.154 | J67: Europe & Central Asia (excluding high income) | K67: ECA | L67: 29316.46 | N67: Europe & Central Asia (excluding high income) | O67: ECA | P67: 16016.953
... A71: Panama | B71: =VLOOKUP(A71,$J$3:$L$268,3,FALSE) -> 41369.423 | C71: =VLOOKUP(A71,'2025'!$B$2:$H$105,2,FALSE)/100 -> 0.112 | D71: =VLOOKUP(A71,$N$3:$P$268,3,FALSE) -> 27245.279 | E71: =VLOOKUP(A71,'2015'!$B$2:$H$122,2,FALSE)/100 -> 0.108 | J71: Euro area | K71: EMU | L71: 66098.011 | N71: Euro area | O71: EMU | P71: 41183.56
A72: Peru | B72: =VLOOKUP(A72,$J$3:$L$268,3,FALSE) -> 17802.418 | C72: =VLOOKUP(A72,'2025'!$B$2:$H$105,2,FALSE)/100 -> 0.184 | D72: =VLOOKUP(A72,$N$3:$P$268,3,FALSE) -> 11600.387 | E72: =VLOOKUP(A72,'2015'!$B$2:$H$122,2,FALSE)/100 -> 0.163 | J72: Eritrea | K72: ERI | N72: Eritrea | O72: ERI
A73: Philippines | B73: =VLOOKUP(A73,$J$3:$L$268,3,FALSE) -> 11794.138 | C73: =VLOOKUP(A73,'2025'!$B$2:$H$105,2,FALSE)/100 -> 0.222 | D73: =VLOOKUP(A73,$N$3:$P$268,3,FALSE) -> 6894.267 | E73: =VLOOKUP(A73,'2015'!$B$2:$H$122,2,FALSE)/100 -> 0.185 | J73: Spain | K73: ESP | L73: 57965.295 | N73: Spain | O73: ESP | P73: 35228.633
A74: Poland | B74: =VLOOKUP(A74,$J$3:$L$268,3,FALSE) -> 51262.511 | C74: =VLOOKUP(A74,'2025'!$B$2:$H$105,2,FALSE)/100 -> 0.11 | D74: =VLOOKUP(A74,$N$3:$P$268,3,FALSE) -> 26988.107 | E74: =VLOOKUP(A74,'2015'!$B$2:$H$122,2,FALSE)/100 -> 0.106 | J74: Estonia | K74: EST | L74: 49968.711 | N74: Estonia | O74: EST | P74: 29712.63
A75: Portugal | B75: =VLOOKUP(A75,$J$3:$L$268,3,FALSE) -> 51679.888 | C75: =VLOOKUP(A75,'2025'!$B$2:$H$105,2,FALSE)/100 -> 0.147 | D75: =VLOOKUP(A75,$N$3:$P$268,3,FALSE) -> 29608.007 | E75: =VLOOKUP(A75,'2015'!$B$2:$H$122,2,FALSE)/100 -> 0.083 | J75: Ethiopia | K75: ETH | L75: 3287.5349 | N75: Ethiopia | O75: ETH | P75: 1632.6182
A76: Qatar | B76: =VLOOKUP(A76,$J$3:$L$268,3,FALSE) -> 126046.35 | C76: =VLOOKUP(A76,'2025'!$B$2:$H$105,2,FALSE)/100 -> 0.052 | D76: =VLOOKUP(A76,$N$3:$P$268,3,FALSE) -> 102545.86 | E76: =VLOOKUP(A76,'2015'!$B$2:$H$122,2,FALSE)/100 -> 0.066 | J76: European Union | K76: EUU | L76: 63610.227 | N76: European Union | O76: EUU | P76: 38444.682
A77: Romania | B77: =VLOOKUP(A77,$J$3:$L$268,3,FALSE) -> 49558.669 | C77: =VLOOKUP(A77,'2025'!$B$2:$H$105,2,FALSE)/100 -> 0.103 | D77: =VLOOKUP(A77,$N$3:$P$268,3,FALSE) -> 20201.858 | E77: =VLOOKUP(A77,'2015'!$B$2:$H$122,2,FALSE)/100 -> 0.118 | J77: Fragile and conflict affected situations | K77: FCS | L77: 6394.5659 | N77: Fragile and conflict affected situations | O77: FCS | P77: 4942.5258
A78: Russian Federation | B78: =VLOOKUP(A78,$J$3:$L$268,3,FALSE) -> 47404.965 | C78: =VLOOKUP(A78,'2025'!$B$2:$H$105,2,FALSE)/100 -> #N/A | D78: =VLOOKUP(A78,$N$3:$P$268,3,FALSE) -> 23994.014 | E78: =VLOOKUP(A78,'2015'!$B$2:$H$122,2,FALSE)/100 -> #N/A | J78: Finland | K78: FIN | L78: 65378.384 | N78: Finland | O78: FIN | P78: 42257.859
A79: Saudi Arabia | B79: =VLOOKUP(A79,$J$3:$L$268,3,FALSE) -> 71375.373 | C79: =VLOOKUP(A79,'2025'!$B$2:$H$105,2,FALSE)/100 -> 0.031 | D79: =VLOOKUP(A79,$N$3:$P$268,3,FALSE) -> 53930.827 | E79: =VLOOKUP(A79,'2015'!$B$2:$H$122,2,FALSE)/100 -> 0.031 | J79: Fiji | K79: FJI | L79: 15450.299 | N79: Fiji | O79: FJI | P79: 11519.301
A80: Serbia | B80: =VLOOKUP(A80,$J$3:$L$268,3,FALSE) -> 32781.014 | C80: =VLOOKUP(A80,'2025'!$B$2:$H$105,2,FALSE)/100 -> 0.16 | D80: =VLOOKUP(A80,$N$3:$P$268,3,FALSE) -> 14523.539 | E80: =VLOOKUP(A80,'2015'!$B$2:$H$122,2,FALSE)/100 -> 0.171 | J80: France | K80: FRA | L80: 62556.918 | N80: France | O80: FRA | P80: 40905.177
A81: Singapore | B81: =VLOOKUP(A81,$J$3:$L$268,3,FALSE) -> 150689.3 | C81: =VLOOKUP(A81,'2025'!$B$2:$H$105,2,FALSE)/100 -> 0.232 | D81: =VLOOKUP(A81,$N$3:$P$268,3,FALSE) -> 87156.187 | E81: =VLOOKUP(A81,'2015'!$B$2:$H$122,2,FALSE)/100 -> 0.214 | J81: Faroe Islands | K81: FRO | L81: 81908.778 | N81: Faroe Islands | O81: FRO | P81: 53684.367
A82: Slovak Republic | B82: =VLOOKUP(A82,$J$3:$L$268,3,FALSE) -> 48132.356 | C82: =VLOOKUP(A82,'2025'!$B$2:$H$105,2,FALSE)/100 -> #N/A | D82: =VLOOKUP(A82,$N$3:$P$268,3,FALSE) -> 30147.99 | E82: =VLOOKUP(A82,'2015'!$B$2:$H$122,2,FALSE)/100 -> #N/A | J82: Micronesia, Fed. Sts. | K82: FSM | L82: 4346.8425 | N82: Micronesia, Fed. Sts. | O82: FSM | P82: 3288.9216
A83: Slovenia | B83: =VLOOKUP(A83,$J$3:$L$268,3,FALSE) -> 57186.371 | C83: =VLOOKUP(A83,'2025'!$B$2:$H$105,2,FALSE)/100 -> 0.13 | D83: =VLOOKUP(A83,$N$3:$P$268,3,FALSE) -> 31336.204 | E83: =VLOOKUP(A83,'2015'!$B$2:$H$122,2,FALSE)/100 -> 0.106 | J83: Gabon | K83: GAB | L83: 21510.173 | N83: Gabon | O83: GAB | P83: 14306.434
A84: South Africa | B84: =VLOOKUP(A84,$J$3:$L$268,3,FALSE) -> 15456.199 | C84: =VLOOKUP(A84,'2025'!$B$2:$H$105,2,FALSE)/100 -> 0.032 | D84: =VLOOKUP(A84,$N$3:$P$268,3,FALSE) -> 13397.523 | E84: =VLOOKUP(A84,'2015'!$B$2:$H$122,2,FALSE)/100 -> 0.031 | J84: United Kingdom | K84: GBR | L84: 62009.491 | N84: United Kingdom | O84: GBR | P84: 42515.279
... A86: Sri Lanka | B86: =VLOOKUP(A86,$J$3:$L$268,3,FALSE) -> 15632.592 | C86: =VLOOKUP(A86,'2025'!$B$2:$H$105,2,FALSE)/100 -> 0.342 | D86: =VLOOKUP(A86,$N$3:$P$268,3,FALSE) -> 12227.171 | E86: =VLOOKUP(A86,'2015'!$B$2:$H$122,2,FALSE)/100 -> 0.143 | J86: Ghana | K86: GHA | L86: 8019.997 | N86: Ghana | O86: GHA | P86: 5191.3705
A87: Sweden | B87: =VLOOKUP(A87,$J$3:$L$268,3,FALSE) -> 71844.913 | C87: =VLOOKUP(A87,'2025'!$B$2:$H$105,2,FALSE)/100 -> 0.077 | D87: =VLOOKUP(A87,$N$3:$P$268,3,FALSE) -> 48772.07 | E87: =VLOOKUP(A87,'2015'!$B$2:$H$122,2,FALSE)/100 -> 0.092 | J87: Gibraltar | K87: GIB | N87: Gibraltar | O87: GIB
A88: Switzerland | B88: =VLOOKUP(A88,$J$3:$L$268,3,FALSE) -> 96497.695 | C88: =VLOOKUP(A88,'2025'!$B$2:$H$105,2,FALSE)/100 -> 0.11 | D88: =VLOOKUP(A88,$N$3:$P$268,3,FALSE) -> 65265.046 | E88: =VLOOKUP(A88,'2015'!$B$2:$H$122,2,FALSE)/100 -> 0.073 | J88: Guinea | K88: GIN | L88: 4565.3008 | N88: Guinea | O88: GIN | P88: 1929.6809
A89: Thailand | B89: =VLOOKUP(A89,$J$3:$L$268,3,FALSE) -> 24712.066 | C89: =VLOOKUP(A89,'2025'!$B$2:$H$105,2,FALSE)/100 -> 0.252 | D89: =VLOOKUP(A89,$N$3:$P$268,3,FALSE) -> 15791.171 | E89: =VLOOKUP(A89,'2015'!$B$2:$H$122,2,FALSE)/100 -> 0.208 | J89: Gambia, The | K89: GMB | L89: 3475.6125 | N89: Gambia, The | O89: GMB | P89: 1990.3163
A90: Tunisia | B90: =VLOOKUP(A90,$J$3:$L$268,3,FALSE) -> 14521.008 | C90: =VLOOKUP(A90,'2025'!$B$2:$H$105,2,FALSE)/100 -> 0.122 | D90: =VLOOKUP(A90,$N$3:$P$268,3,FALSE) -> 10782.544 | E90: =VLOOKUP(A90,'2015'!$B$2:$H$122,2,FALSE)/100 -> 0.108 | J90: Guinea-Bissau | K90: GNB | L90: 3119.3716 | N90: Guinea-Bissau | O90: GNB | P90: 1729.9426
A91: Turkiye | B91: =VLOOKUP(A91,$J$3:$L$268,3,FALSE) -> 45639.019 | C91: =VLOOKUP(A91,'2025'!$B$2:$H$105,2,FALSE)/100 -> #N/A | D91: =VLOOKUP(A91,$N$3:$P$268,3,FALSE) -> 25890.055 | E91: =VLOOKUP(A91,'2015'!$B$2:$H$122,2,FALSE)/100 -> #N/A | J91: Equatorial Guinea | K91: GNQ | L91: 17566.76 | N91: Equatorial Guinea | O91: GNQ | P91: 19478.701
A92: Ukraine | B92: =VLOOKUP(A92,$J$3:$L$268,3,FALSE) -> 18550.463 | C92: =VLOOKUP(A92,'2025'!$B$2:$H$105,2,FALSE)/100 -> 0.136 | D92: =VLOOKUP(A92,$N$3:$P$268,3,FALSE) -> 9921.834 | E92: =VLOOKUP(A92,'2015'!$B$2:$H$122,2,FALSE)/100 -> 0.174 | J92: Greece | K92: GRC | L92: 44327.21 | N92: Greece | O92: GRC | P92: 26607.726
A93: United Arab Emirates | B93: =VLOOKUP(A93,$J$3:$L$268,3,FALSE) -> 79228.739 | C93: =VLOOKUP(A93,'2025'!$B$2:$H$105,2,FALSE)/100 -> 0.07 | D93: =VLOOKUP(A93,$N$3:$P$268,3,FALSE) -> 73986.064 | E93: =VLOOKUP(A93,'2015'!$B$2:$H$122,2,FALSE)/100 -> 0.062 | J93: Grenada | K93: GRD | L93: 20177.809 | N93: Grenada | O93: GRD | P93: 13214.41
A94: United Kingdom | B94: =VLOOKUP(A94,$J$3:$L$268,3,FALSE) -> 62009.491 | C94: =VLOOKUP(A94,'2025'!$B$2:$H$105,2,FALSE)/100 -> 0.088 | D94: =VLOOKUP(A94,$N$3:$P$268,3,FALSE) -> 42515.279 | E94: =VLOOKUP(A94,'2015'!$B$2:$H$122,2,FALSE)/100 -> 0.086 | J94: Greenland | K94: GRL | N94: Greenland | O94: GRL | P94: 55815.65
A95: United States | B95: =VLOOKUP(A95,$J$3:$L$268,3,FALSE) -> 85809.9 | C95: =VLOOKUP(A95,'2025'!$B$2:$H$105,2,FALSE)/100 -> 0.033 | D95: =VLOOKUP(A95,$N$3:$P$268,3,FALSE) -> 56849.47 | E95: =VLOOKUP(A95,'2015'!$B$2:$H$122,2,FALSE)/100 -> 0.026 | J95: Guatemala | K95: GTM | L95: 14368.661 | N95: Guatemala | O95: GTM | P95: 8934.0026
A96: Uruguay | B96: =VLOOKUP(A96,$J$3:$L$268,3,FALSE) -> 36417.874 | C96: =VLOOKUP(A96,'2025'!$B$2:$H$105,2,FALSE)/100 -> 0.13 | D96: =VLOOKUP(A96,$N$3:$P$268,3,FALSE) -> 22168.611 | E96: =VLOOKUP(A96,'2015'!$B$2:$H$122,2,FALSE)/100 -> 0.112 | J96: Guam | K96: GUM | N96: Guam | O96: GUM
A97: Uzbekistan | B97: =VLOOKUP(A97,$J$3:$L$268,3,FALSE) -> 11878.553 | C97: =VLOOKUP(A97,'2025'!$B$2:$H$105,2,FALSE)/100 -> 0.135 | D97: =VLOOKUP(A97,$N$3:$P$268,3,FALSE) -> 6799.5733 | E97: =VLOOKUP(A97,'2015'!$B$2:$H$122,2,FALSE)/100 -> 0.147 | J97: Guyana | K97: GUY | L97: 80155.039 | N97: Guyana | O97: GUY | P97: 11408.474
A98: Viet Nam | B98: =VLOOKUP(A98,$J$3:$L$268,3,FALSE) -> 16385.507 | C98: =VLOOKUP(A98,'2025'!$B$2:$H$105,2,FALSE)/100 -> #N/A | D98: =VLOOKUP(A98,$N$3:$P$268,3,FALSE) -> 7671.582 | E98: =VLOOKUP(A98,'2015'!$B$2:$H$122,2,FALSE)/100 -> #N/A | J98: High income | K98: HIC | L98: 67051.678 | N98: High income | O98: HIC | P98: 43078.305
J99: Hong Kong SAR, China | K99: HKG | L99: 75195.987 | N99: Hong Kong SAR, China | O99: HKG | P99: 56043.043
J100: Honduras | K100: HND | L100: 7486.0187 | N100: Honduras | O100: HND | P100: 4845.5957
J101: Heavily indebted poor countries (HIPC) | K101: HPC | L101: 3611.7626 | N101: Heavily indebted poor countries (HIPC) | O101: HPC | P101: 2407.8225
J102: Croatia | K102: HRV | L102: 49645.746 | N102: Croatia | O102: HRV | P102: 22187.177
J103: Haiti | K103: HTI | L103: 3193.6714 | N103: Haiti | O103: HTI | P103: 3025.8346
J104: Hungary | K104: HUN | L104: 48552.471 | N104: Hungary | O104: HUN | P104: 26937.732
J105: IBRD only | K105: IBD | L105: 21126.946 | N105: IBRD only | O105: IBD | P105: 11684.143
J106: IDA & IBRD total | K106: IBT | L106: 16790.149 | N106: IDA & IBRD total | O106: IBT | P106: 9673.0234
J107: IDA total | K107: IDA | L107: 5710.1446 | N107: IDA total | O107: IDA | P107: 3818.711
J108: IDA blend | K108: IDB | L108: 7631.6229 | N108: IDA blend | O108: IDB | P108: 5466.8623
...

Sheet Sheet4
C1: 2025 | D1: 2025 | E1: 2025 | F1: 2015 | G1: 2015 | H1: 2015
A2: Income group | B2: Country | C2: GDP per capita | D2: Price to Income | E2: REP price | F2: GDP per capita | G2: Price to Income | H2: REP price | I2: GDP growth | J2: REP growth
A3: =VLOOKUP(B3,'List of economies'!$A$2:$D$219,4,FALSE) -> High income | B3: Australia | C3: 72111.184 | D3: 0.081 | E3: =C3*D3 -> 5841.0059 | F3: 46464.587 | G3: 0.071 | H3: =F3*G3 -> 3298.9857 | I3: =C3/F3-1 -> 0.55196009 | J3: =E3/H3-1 -> 0.77054602 | K3: =J3/I3 -> 1.3960176
A4: =VLOOKUP(B4,'List of economies'!$A$2:$D$219,4,FALSE) -> High income | B4: Austria | C4: 73911.44 | D4: 0.115 | E4: =C4*D4 -> 8499.8156 | F4: 49549.316 | G4: 0.096 | H4: =F4*G4 -> 4756.7344 | I4: =C4/F4-1 -> 0.49167426 | J4: =E4/H4-1 -> 0.78690146 | K4: =J4/I4 -> 1.6004528
A5: =VLOOKUP(B5,'List of economies'!$A$2:$D$219,4,FALSE) -> High income | B5: Belgium | C5: 73514.483 | D5: 0.068 | E5: =C5*D5 -> 4998.9849 | F5: 46071.915 | G5: 0.065 | H5: =F5*G5 -> 2994.6745 | I5: =C5/F5-1 -> 0.59564636 | J5: =E5/H5-1 -> 0.66929157 | K5: =J5/I5 -> 1.1236392
A6: =VLOOKUP(B6,'List of economies'!$A$2:$D$219,4,FALSE) -> High income | B6: Bulgaria | C6: 42224.445 | D6: 0.093 | E6: =C6*D6 -> 3926.8733 | F6: 17652.947 | G6: 0.094 | H6: =F6*G6 -> 1659.377 | I6: =C6/F6-1 -> 1.3919204 | J6: =E6/H6-1 -> 1.3664745 | K6: =J6/I6 -> 0.98171881
A7: =VLOOKUP(B7,'List of economies'!$A$2:$D$219,4,FALSE) -> High income | B7: Canada | C7: 64610.38 | D7: 0.102 | E7: =C7*D7 -> 6590.2587 | F7: 44668.091 | G7: 0.055 | H7: =F7*G7 -> 2456.745 | I7: =C7/F7-1 -> 0.4464549 | J7: =E7/H7-1 -> 1.6825164 | K7: =J7/I7 -> 3.7686144
A8: =VLOOKUP(B8,'List of economies'!$A$2:$D$219,4,FALSE) -> High income | B8: Chile | C8: 36181.157 | D8: 0.156 | E8: =C8*D8 -> 5644.2604 | F8: 22468.313 | G8: 0.108 | H8: =F8*G8 -> 2426.5778 | I8: =C8/F8-1 -> 0.61031927 | J8: =E8/H8-1 -> 1.3260167 | K8: =J8/I8 -> 2.1726608
A9: =VLOOKUP(B9,'List of economies'!$A$2:$D$219,4,FALSE) -> High income | B9: Costa Rica | C9: 31106.764 | D9: 0.103 | E9: =C9*D9 -> 3203.9967 | F9: 17525.14 | G9: 0.057 | H9: =F9*G9 -> 998.93301 | I9: =C9/F9-1 -> 0.77497946 | J9: =E9/H9-1 -> 2.207419 | K9: =J9/I9 -> 2.8483581
A10: =VLOOKUP(B10,'List of economies'!$A$2:$D$219,4,FALSE) -> High income | B10: Croatia | C10: 49645.746 | D10: 0.128 | E10: =C10*D10 -> 6354.6554 | F10: 22187.177 | G10: 0.125 | H10: =F10*G10 -> 2773.3972 | I10: =C10/F10-1 -> 1.2375873 | J10: =E10/H10-1 -> 1.2912894 | K10: =J10/I10 -> 1.0433926
A11: =VLOOKUP(B11,'List of economies'!$A$2:$D$219,4,FALSE) -> High income | B11: Cyprus | C11: 62312.074 | D11: 0.082 | E11: =C11*D11 -> 5109.5901 | F11: 29315.725 | G11: 0.074 | H11: =F11*G11 -> 2169.3636 | I11: =C11/F11-1 -> 1.1255512 | J11: =E11/H11-1 -> 1.3553405 | K11: =J11/I11 -> 1.2041571
A12: =VLOOKUP(B12,'List of economies'!$A$2:$D$219,4,FALSE) -> High income | B12: Denmark | C12: 81878.235 | D12: 0.065 | E12: =C12*D12 -> 5322.0853 | F12: 48897.21 | G12: 0.05 | H12: =F12*G12 -> 2444.8605 | I12: =C12/F12-1 -> 0.67449707 | J12: =E12/H12-1 -> 1.1768462 | K12: =J12/I12 -> 1.7447758
A13: =VLOOKUP(B13,'List of economies'!$A$2:$D$219,4,FALSE) -> High income | B13: Estonia | C13: 49968.711 | D13: 0.114 | E13: =C13*D13 -> 5696.433 | F13: 29712.63 | G13: 0.116 | H13: =F13*G13 -> 3446.6651 | I13: =C13/F13-1 -> 0.68173302 | J13: =E13/H13-1 -> 0.65273762 | K13: =J13/I13 -> 0.95746811
A14: =VLOOKUP(B14,'List of economies'!$A$2:$D$219,4,FALSE) -> High income | B14: Finland | C14: 65378.384 | D14: 0.08 | E14: =C14*D14 -> 5230.2707 | F14: 42257.859 | G14: 0.07 | H14: =F14*G14 -> 2958.0502 | I14: =C14/F14-1 -> 0.54712958 | J14: =E14/H14-1 -> 0.76814809 | K14: =J14/I14 -> 1.4039601
... A86: =VLOOKUP(B86,'List of economies'!$A$2:$D$219,4,FALSE) -> Upper middle income | B86: Ukraine | C86: 18550.463 | D86: 0.136 | E86: =C86*D86 -> 2522.863 | F86: 9921.834 | G86: 0.174 | H86: =F86*G86 -> 1726.3991 | I86: =C86/F86-1 -> 0.86966068 | J86: =E86/H86-1 -> 0.46134398 | K86: =J86/I86 -> 0.53048734
B87: Turkiye | C87: 45639.019 | D87: 0.107 | E87: =C87*D87 -> 4883.3751 | F87: 25890.055 | G87: 0.067 | H87: =F87*G87 -> 1734.6337 | I87: =C87/F87-1 -> 0.76280118 | J87: =E87/H87-1 -> 1.8152198 | K87: =J87/I87 -> 2.3796762

Sheet Sheet5
A1: Ok or not? | B1: Income group | C1: Country | D1: REP growth per income growth
A2: 1 | B2: =VLOOKUP(C2,'List of economies'!$A$2:$D$219,4,FALSE) -> High income | C2: Qatar | D2: -0.13772537
A3: 1 | B3: =VLOOKUP(C3,'List of economies'!$A$2:$D$219,4,FALSE) -> Lower middle income | C3: Jordan | D3: -0.085681991
A4: 1 | B4: =VLOOKUP(C4,'List of economies'!$A$2:$D$219,4,FALSE) -> Upper middle income | C4: Algeria | D4: 0.071427344
A5: 1 | B5: =VLOOKUP(C5,'List of economies'!$A$2:$D$219,4,FALSE) -> Upper middle income | C5: El Salvador | D5: 0.22604105
A6: 1 | B6: =VLOOKUP(C6,'List of economies'!$A$2:$D$219,4,FALSE) -> Lower middle income | C6: Morocco | D6: 0.3323339
A7: 1 | B7: =VLOOKUP(C7,'List of economies'!$A$2:$D$219,4,FALSE) -> High income | C7: Latvia | D7: 0.38586813
B8: =VLOOKUP(C8,'List of economies'!$A$2:$D$219,4,FALSE) -> Upper middle income | C8: Ecuador | D8: 0.39200325
B9: =VLOOKUP(C9,'List of economies'!$A$2:$D$219,4,FALSE) -> Upper middle income | C9: Indonesia | D9: 0.45783236
A10: 1 | B10: =VLOOKUP(C10,'List of economies'!$A$2:$D$219,4,FALSE) -> High income | C10: Sweden | D10: 0.49231032
A11: 1 | B11: =VLOOKUP(C11,'List of economies'!$A$2:$D$219,4,FALSE) -> Upper middle income | C11: Kazakhstan | D11: 0.51021156
A12: 1 | B12: =VLOOKUP(C12,'List of economies'!$A$2:$D$219,4,FALSE) -> Upper middle income | C12: Belarus | D12: 0.51292143
A13: 1 | B13: =VLOOKUP(C13,'List of economies'!$A$2:$D$219,4,FALSE) -> High income | C13: Italy | D13: 0.52655885
A14: 1 | B14: =VLOOKUP(C14,'List of economies'!$A$2:$D$219,4,FALSE) -> Upper middle income | C14: Ukraine | D14: 0.53048734
B15: =VLOOKUP(C15,'List of economies'!$A$2:$D$219,4,FALSE) -> Upper middle income | C15: Mauritius | D15: 0.55173195
A16: 1 | B16: =VLOOKUP(C16,'List of economies'!$A$2:$D$219,4,FALSE) -> Upper middle income | C16: Moldova | D16: 0.56074104
A17: 1 | B17: =VLOOKUP(C17,'List of economies'!$A$2:$D$219,4,FALSE) -> Upper middle income | C17: North Macedonia | D17: 0.58023705
A18: 1 | B18: =VLOOKUP(C18,'List of economies'!$A$2:$D$219,4,FALSE) -> Upper middle income | C18: Montenegro | D18: 0.65013701
A19: 1 | B19: =VLOOKUP(C19,'List of economies'!$A$2:$D$219,4,FALSE) -> High income | C19: Spain | D19: 0.70787898
A20: 1 | B20: =VLOOKUP(C20,'List of economies'!$A$2:$D$219,4,FALSE) -> Upper middle income | C20: Georgia | D20: 0.70952057
A21: 1 | B21: =VLOOKUP(C21,'List of economies'!$A$2:$D$219,4,FALSE) -> Upper middle income | C21: Brazil | D21: 0.73307972
A22: 1 | B22: =VLOOKUP(C22,'List of economies'!$A$2:$D$219,4,FALSE) -> High income | C22: Oman | D22: 0.7704364
A23: 1 | B23: =VLOOKUP(C23,'List of economies'!$A$2:$D$219,4,FALSE) -> High income | C23: Romania | D23: 0.78540479
A24: 1 | B24: =VLOOKUP(C24,'List of economies'!$A$2:$D$219,4,FALSE) -> Lower middle income | C24: Uzbekistan | D24: 0.80908019
B25: =VLOOKUP(C25,'List of economies'!$A$2:$D$219,4,FALSE) -> Upper middle income | C25: Iraq | D25: 0.84159347
A26: 1 | B26: =VLOOKUP(C26,'List of economies'!$A$2:$D$219,4,FALSE) -> Upper middle income | C26: Serbia | D26: 0.884501
A27: 1 | B27: =VLOOKUP(C27,'List of economies'!$A$2:$D$219,4,FALSE) -> Upper middle income | C27: Azerbaijan | D27: 0.90720516
A28: 1 | B28: =VLOOKUP(C28,'List of economies'!$A$2:$D$219,4,FALSE) -> High income | C28: Lithuania | D28: 0.9243801
A29: 1 | B29: =VLOOKUP(C29,'List of economies'!$A$2:$D$219,4,FALSE) -> High income | C29: Estonia | D29: 0.95746811
A30: 1 | B30: =VLOOKUP(C30,'List of economies'!$A$2:$D$219,4,FALSE) -> High income | C30: Bulgaria | D30: 0.98171881
A31: 1 | B31: =VLOOKUP(C31,'List of economies'!$A$2:$D$219,4,FALSE) -> High income | C31: Saudi Arabia | D31: 1
A32: 1 | B32: =VLOOKUP(C32,'List of economies'!$A$2:$D$219,4,FALSE) -> Lower middle income | C32: Pakistan | D32: 1
A33: 1 | B33: =VLOOKUP(C33,'List of economies'!$A$2:$D$219,4,FALSE) -> High income | C33: Croatia | D33: 1.0433926
A34: 1 | B34: =VLOOKUP(C34,'List of economies'!$A$2:$D$219,4,FALSE) -> High income | C34: United Kingdom | D34: 1.0739748
A35: 1 | B35: =VLOOKUP(C35,'List of economies'!$A$2:$D$219,4,FALSE) -> High income | C35: Poland | D35: 1.0796903
A36: 1 | B36: =VLOOKUP(C36,'List of economies'!$A$2:$D$219,4,FALSE) -> Upper middle income | C36: Albania | D36: 1.0835676
A37: 1 | B37: =VLOOKUP(C37,'List of economies'!$A$2:$D$219,4,FALSE) -> Upper middle income | C37: Malaysia | D37: 1.0971715
B38: =VLOOKUP(C38,'List of economies'!$A$2:$D$219,4,FALSE) -> Upper middle income | C38: Bosnia And Herzegovina | D38: 1.1064672
B39: =VLOOKUP(C39,'List of economies'!$A$2:$D$219,4,FALSE) -> High income | C39: Panama | D39: 1.108481
A40: 1 | B40: =VLOOKUP(C40,'List of economies'!$A$2:$D$219,4,FALSE) -> High income | C40: Luxembourg | D40: 1.1172264
A41: 1 | B41: =VLOOKUP(C41,'List of economies'!$A$2:$D$219,4,FALSE) -> High income | C41: Belgium | D41: 1.1236392
A42: 1 | B42: =VLOOKUP(C42,'List of economies'!$A$2:$D$219,4,FALSE) -> Lower middle income | C42: India | D42: 1.1541355
A43: 1 | B43: =VLOOKUP(C43,'List of economies'!$A$2:$D$219,4,FALSE) -> Upper middle income | C43: China | D43: 1.1580518
A44: 1 | B44: =VLOOKUP(C44,'List of economies'!$A$2:$D$219,4,FALSE) -> High income | C44: France | D44: 1.1787154
A45: 1 | B45: =VLOOKUP(C45,'List of economies'!$A$2:$D$219,4,FALSE) -> High income | C45: Singapore | D45: 1.1994991
A46: 1 | B46: =VLOOKUP(C46,'List of economies'!$A$2:$D$219,4,FALSE) -> High income | C46: Cyprus | D46: 1.2041571
A47: 1 | B47: =VLOOKUP(C47,'List of economies'!$A$2:$D$219,4,FALSE) -> High income | C47: Ireland | D47: 1.2122096
A48: 1 | B48: =VLOOKUP(C48,'List of economies'!$A$2:$D$219,4,FALSE) -> High income | C48: Norway | D48: 1.2246058
B49: =VLOOKUP(C49,'List of economies'!$A$2:$D$219,4,FALSE) -> Upper middle income | C49: South Africa | D49: 1.2421883
B50: =VLOOKUP(C50,'List of economies'!$A$2:$D$219,4,FALSE) -> Lower middle income | C50: Bangladesh | D50: 1.3094188
B51: =VLOOKUP(C51,'List of economies'!$A$2:$D$219,4,FALSE) -> Upper middle income | C51: Peru | D51: 1.3698084
A52: 1 | B52: =VLOOKUP(C52,'List of economies'!$A$2:$D$219,4,FALSE) -> High income | C52: Australia | D52: 1.3960176
A53: 1 | B53: =VLOOKUP(C53,'List of economies'!$A$2:$D$219,4,FALSE) -> High income | C53: Finland | D53: 1.4039601
A54: 1 | B54: =VLOOKUP(C54,'List of economies'!$A$2:$D$219,4,FALSE) -> High income | C54: Uruguay | D54: 1.4107492
A55: 1 | B55: =VLOOKUP(C55,'List of economies'!$A$2:$D$219,4,FALSE) -> High income | C55: Iceland | D55: 1.4721176
A56: 1 | B56: =VLOOKUP(C56,'List of economies'!$A$2:$D$219,4,FALSE) -> Lower middle income | C56: Philippines | D56: 1.4814061
A57: 1 | B57: =VLOOKUP(C57,'List of economies'!$A$2:$D$219,4,FALSE) -> High income | C57: Slovenia | D57: 1.500881
B58: =VLOOKUP(C58,'List of economies'!$A$2:$D$219,4,FALSE) -> Lower middle income | C58: Tunisia | D58: 1.5035097
B59: =VLOOKUP(C59,'List of economies'!$A$2:$D$219,4,FALSE) -> Lower middle income | C59: Bolivia | D59: 1.5158425
A60: 1 | B60: =VLOOKUP(C60,'List of economies'!$A$2:$D$219,4,FALSE) -> Upper middle income | C60: Thailand | D60: 1.5859897
A61: 1 | B61: =VLOOKUP(C61,'List of economies'!$A$2:$D$219,4,FALSE) -> High income | C61: Netherlands | D61: 1.5920009
A62: 1 | B62: =VLOOKUP(C62,'List of economies'!$A$2:$D$219,4,FALSE) -> High income | C62: Austria | D62: 1.6004528
B63: =VLOOKUP(C63,'List of economies'!$A$2:$D$219,4,FALSE) -> Upper middle income | C63: Colombia | D63: 1.6368328
A64: 1 | B64: =VLOOKUP(C64,'List of economies'!$A$2:$D$219,4,FALSE) -> High income | C64: Denmark | D64: 1.7447758
A65: 1 | B65: =VLOOKUP(C65,'List of economies'!$A$2:$D$219,4,FALSE) -> High income | C65: Israel | D65: 1.7511082
A66: 1 | B66: =VLOOKUP(C66,'List of economies'!$A$2:$D$219,4,FALSE) -> Upper middle income | C66: Armenia | D66: 1.7821115
A67: 1 | B67: =VLOOKUP(C67,'List of economies'!$A$2:$D$219,4,FALSE) -> High income | C67: New Zealand | D67: 1.7964739
A68: 1 | B68: =VLOOKUP(C68,'List of economies'!$A$2:$D$219,4,FALSE) -> High income | C68: United States | D68: 1.7977321
A69: 1 | B69: =VLOOKUP(C69,'List of economies'!$A$2:$D$219,4,FALSE) -> High income | C69: Greece | D69: 1.8510626
B70: =VLOOKUP(C70,'List of economies'!$A$2:$D$219,4,FALSE) -> Upper middle income | C70: Dominican Republic | D70: 1.940104
A71: 1 | B71: =VLOOKUP(C71,'List of economies'!$A$2:$D$219,4,FALSE) -> High income | C71: Germany | D71: 2.0250015
B72: =VLOOKUP(C72,'List of economies'!$A$2:$D$219,4,FALSE) -> High income | C72: Malta | D72: 2.1217123
A73: 1 | B73: =VLOOKUP(C73,'List of economies'!$A$2:$D$219,4,FALSE) -> High income | C73: Hungary | D73: 2.1492528
B74: =VLOOKUP(C74,'List of economies'!$A$2:$D$219,4,FALSE) -> High income | C74: Chile | D74: 2.1726608
B75: =VLOOKUP(C75,'List of economies'!$A$2:$D$219,4,FALSE) -> Lower middle income | C75: Nepal | D75: 2.2991932
A76: 1 | B76: =VLOOKUP(C76,'List of economies'!$A$2:$D$219,4,FALSE) -> High income | C76: Kuwait | D76: 2.4376196
A77: 1 | B77: =VLOOKUP(C77,'List of economies'!$A$2:$D$219,4,FALSE) -> Upper middle income | C77: Argentina | D77: 2.5194212
A78: 1 | B78: =VLOOKUP(C78,'List of economies'!$A$2:$D$219,4,FALSE) -> High income | C78: Japan | D78: 2.5232262
A79: 1 | B79: =VLOOKUP(C79,'List of economies'!$A$2:$D$219,4,FALSE) -> High income | C79: Switzerland | D79: 2.5659828
A80: 1 | B80: =VLOOKUP(C80,'List of economies'!$A$2:$D$219,4,FALSE) -> High income | C80: Portugal | D80: 2.8054443
B81: =VLOOKUP(C81,'List of economies'!$A$2:$D$219,4,FALSE) -> High income | C81: Costa Rica | D81: 2.8483581
A82: 1 | B82: =VLOOKUP(C82,'List of economies'!$A$2:$D$219,4,FALSE) -> High income | C82: United Arab Emirates | D82: 2.9499707
A83: 1 | B83: =VLOOKUP(C83,'List of economies'!$A$2:$D$219,4,FALSE) -> High income | C83: Canada | D83: 3.7686144
A84: 1 | B84: =VLOOKUP(C84,'List of economies'!$A$2:$D$219,4,FALSE) -> Upper middle income | C84: Mexico | D84: 4.2134544
B85: =VLOOKUP(C85,'List of economies'!$A$2:$D$219,4,FALSE) -> Lower middle income | C85: Sri Lanka | D85: 7.3881813

Sheet Sheet6
A1: Income group | B1: Country | C1: REP growth per income growth
A2: High income | B2: Qatar | C2: -0.13772537
A3: Lower middle income | B3: Jordan | C3: -0.085681991
A4: Upper middle income | B4: El Salvador | C4: 0.22604105
A5: High income | B5: Latvia | C5: 0.38586813
A6: High income | B6: Sweden | C6: 0.49231032
A7: Upper middle income | B7: Kazakhstan | C7: 0.51021156
A8: Upper middle income | B8: Belarus | C8: 0.51292143
A9: High income | B9: Italy | C9: 0.52655885
A10: Upper middle income | B10: Ukraine | C10: 0.53048734
A11: Upper middle income | B11: Moldova | C11: 0.56074104
A12: High income | B12: Spain | C12: 0.70787898
A13: Upper middle income | B13: Georgia | C13: 0.70952057
... A62: Upper middle income | B62: Mexico | C62: 4.2134544

Sheet Sheet1
B1: Income | C1: Price to income | D1: Price | E1: Income | F1: Price to income | G1: Price | H1: delta Price
B2: 1000 | C2: 1.5 | D2: =B2*C2 -> 1500 | E2: 2000 | F2: 2 | G2: =E2*F2 -> 4000 | H2: =G2/D2-1 -> 1.6666667

Sheet List of economies
A1: Economy | B1: Code | C1: Region | D1: Income group | E1: Lending category
A2: Afghanistan | B2: AFG | C2: Middle East, North Africa, Afghanistan & Pakistan | D2: Low income | E2: IDA
A3: Albania | B3: ALB | C3: Europe & Central Asia | D3: Upper middle income | E3: IBRD
A4: Algeria | B4: DZA | C4: Middle East, North Africa, Afghanistan & Pakistan | D4: Upper middle income | E4: IBRD
A5: American Samoa | B5: ASM | C5: East Asia & Pacific | D5: High income
A6: Andorra | B6: AND | C6: Europe & Central Asia | D6: High income
A7: Angola | B7: AGO | C7: Sub-Saharan Africa | D7: Lower middle income | E7: IBRD
A8: Antigua and Barbuda | B8: ATG | C8: Latin America & Caribbean | D8: High income | E8: IBRD
A9: Argentina | B9: ARG | C9: Latin America & Caribbean | D9: Upper middle income | E9: IBRD
A10: Armenia | B10: ARM | C10: Europe & Central Asia | D10: Upper middle income | E10: IBRD
A11: Aruba | B11: ABW | C11: Latin America & Caribbean | D11: High income
A12: Australia | B12: AUS | C12: East Asia & Pacific | D12: High income
A13: Austria | B13: AUT | C13: Europe & Central Asia | D13: High income
A14: Azerbaijan | B14: AZE | C14: Europe & Central Asia | D14: Upper middle income | E14: IBRD
A15: Bahamas, The | B15: BHS | C15: Latin America & Caribbean | D15: High income
A16: Bahrain | B16: BHR | C16: Middle East, North Africa, Afghanistan & Pakistan | D16: High income
A17: Bangladesh | B17: BGD | C17: South Asia | D17: Lower middle income | E17: IDA
A18: Barbados | B18: BRB | C18: Latin America & Caribbean | D18: High income | E18: IBRD
A19: Belarus | B19: BLR | C19: Europe & Central Asia | D19: Upper middle income | E19: IBRD
A20: Belgium | B20: BEL | C20: Europe & Central Asia | D20: High income
A21: Belize | B21: BLZ | C21: Latin America & Caribbean | D21: Upper middle income | E21: Blend
A22: Benin | B22: BEN | C22: Sub-Saharan Africa | D22: Lower middle income | E22: IDA
A23: Bermuda | B23: BMU | C23: North America | D23: High income
A24: Bhutan | B24: BTN | C24: South Asia | D24: Lower middle income | E24: IDA
A25: Bolivia | B25: BOL | C25: Latin America & Caribbean | D25: Lower middle income | E25: IBRD
A26: Bosnia and Herzegovina | B26: BIH | C26: Europe & Central Asia | D26: Upper middle income | E26: IBRD
A27: Botswana | B27: BWA | C27: Sub-Saharan Africa | D27: Upper middle income | E27: IBRD
A28: Brazil | B28: BRA | C28: Latin America & Caribbean | D28: Upper middle income | E28: IBRD
A29: British Virgin Islands | B29: VGB | C29: Latin America & Caribbean | D29: High income
A30: Brunei Darussalam | B30: BRN | C30: East Asia & Pacific | D30: High income
A31: Bulgaria | B31: BGR | C31: Europe & Central Asia | D31: High income | E31: IBRD
A32: Burkina Faso | B32: BFA | C32: Sub-Saharan Africa | D32: Low income | E32: IDA
A33: Burundi | B33: BDI | C33: Sub-Saharan Africa | D33: Low income | E33: IDA
A34: Cabo Verde | B34: CPV | C34: Sub-Saharan Africa | D34: Upper middle income | E34: Blend
A35: Cambodia | B35: KHM | C35: East Asia & Pacific | D35: Lower middle income | E35: IDA
A36: Cameroon | B36: CMR | C36: Sub-Saharan Africa | D36: Lower middle income | E36: Blend
A37: Canada | B37: CAN | C37: North America | D37: High income
A38: Cayman Islands | B38: CYM | C38: Latin America & Caribbean | D38: High income
A39: Central African Republic | B39: CAF | C39: Sub-Saharan Africa | D39: Low income | E39: IDA
A40: Chad | B40: TCD | C40: Sub-Saharan Africa | D40: Low income | E40: IDA
A41: Channel Islands | B41: CHI | C41: Europe & Central Asia | D41: High income
A42: Chile | B42: CHL | C42: Latin America & Caribbean | D42: High income | E42: IBRD
A43: China | B43: CHN | C43: East Asia & Pacific | D43: Upper middle income | E43: IBRD
A44: Colombia | B44: COL | C44: Latin America & Caribbean | D44: Upper middle income | E44: IBRD
A45: Comoros | B45: COM | C45: Sub-Saharan Africa | D45: Lower middle income | E45: IDA
A46: Congo, Dem. Rep. | B46: COD | C46: Sub-Saharan Africa | D46: Low income | E46: IDA
A47: Congo, Rep. | B47: COG | C47: Sub-Saharan Africa | D47: Lower middle income | E47: Blend
A48: Costa Rica | B48: CRI | C48: Latin America & Caribbean | D48: High income | E48: IBRD
A49: Côte d’Ivoire | B49: CIV | C49: Sub-Saharan Africa | D49: Lower middle income | E49: Blend
A50: Croatia | B50: HRV | C50: Europe & Central Asia | D50: High income | E50: IBRD
A51: Cuba | B51: CUB | C51: Latin America & Caribbean | D51: Upper middle income
A52: Curaçao | B52: CUW | C52: Latin America & Caribbean | D52: High income
A53: Cyprus | B53: CYP | C53: Europe & Central Asia | D53: High income
A54: Czechia | B54: CZE | C54: Europe & Central Asia | D54: High income
A55: Denmark | B55: DNK | C55: Europe & Central Asia | D55: High income
A56: Djibouti | B56: DJI | C56: Middle East, North Africa, Afghanistan & Pakistan | D56: Lower middle income | E56: IDA
A57: Dominica | B57: DMA | C57: Latin America & Caribbean | D57: Upper middle income | E57: Blend
A58: Dominican Republic | B58: DOM | C58: Latin America & Caribbean | D58: Upper middle income | E58: IBRD
A59: Ecuador | B59: ECU | C59: Latin America & Caribbean | D59: Upper middle income | E59: IBRD
A60: Egypt, Arab Rep. | B60: EGY | C60: Middle East, North Africa, Afghanistan & Pakistan | D60: Lower middle income | E60: IBRD
A61: El Salvador | B61: SLV | C61: Latin America & Caribbean | D61: Upper middle income | E61: IBRD
A62: Equatorial Guinea | B62: GNQ | C62: Sub-Saharan Africa | D62: Upper middle income | E62: IBRD
A63: Eritrea | B63: ERI | C63: Sub-Saharan Africa | D63: Low income | E63: IDA
A64: Estonia | B64: EST | C64: Europe & Central Asia | D64: High income
A65: Eswatini | B65: SWZ | C65: Sub-Saharan Africa | D65: Lower middle income | E65: Blend
A66: Ethiopia | B66: ETH | C66: Sub-Saharan Africa | E66: IDA
A67: Faroe Islands | B67: FRO | C67: Europe & Central Asia | D67: High income
A68: Fiji | B68: FJI | C68: East Asia & Pacific | D68: Upper middle income | E68: Blend
A69: Finland | B69: FIN | C69: Europe & Central Asia | D69: High income
A70: France | B70: FRA | C70: Europe & Central Asia | D70: High income
A71: French Polynesia | B71: PYF | C71: East Asia & Pacific | D71: High income
A72: Gabon | B72: GAB | C72: Sub-Saharan Africa | D72: Upper middle income | E72: IBRD
A73: Gambia, The | B73: GMB | C73: Sub-Saharan Africa | D73: Low income | E73: IDA
A74: Georgia | B74: GEO | C74: Europe & Central Asia | D74: Upper middle income | E74: IBRD
A75: Germany | B75: DEU | C75: Europe & Central Asia | D75: High income
A76: Ghana | B76: GHA | C76: Sub-Saharan Africa | D76: Lower middle income | E76: IDA
A77: Gibraltar | B77: GIB | C77: Europe & Central Asia | D77: High income
A78: Greece | B78: GRC | C78: Europe & Central Asia | D78: High income
A79: Greenland | B79: GRL | C79: Europe & Central Asia | D79: High income
A80: Grenada | B80: GRD | C80: Latin America & Caribbean | D80: Upper middle income | E80: Blend
A81: Guam | B81: GUM | C81: East Asia & Pacific | D81: High income
A82: Guatemala | B82: GTM | C82: Latin America & Caribbean | D82: Upper middle income | E82: IBRD
A83: Guinea | B83: GIN | C83: Sub-Saharan Africa | D83: Lower middle income | E83: IDA
A84: Guinea-Bissau | B84: GNB | C84: Sub-Saharan Africa | D84: Low income | E84: IDA
A85: Guyana | B85: GUY | C85: Latin America & Caribbean | D85: High income | E85: IDA
A86: Haiti | B86: HTI | C86: Latin America & Caribbean | D86: Lower middle income | E86: IDA
A87: Honduras | B87: HND | C87: Latin America & Caribbean | D87: Lower middle income | E87: IDA
A88: Hong Kong SAR, China | B88: HKG | C88: East Asia & Pacific | D88: High income
A89: Hungary | B89: HUN | C89: Europe & Central Asia | D89: High income
A90: Iceland | B90: ISL | C90: Europe & Central Asia | D90: High income
A91: India | B91: IND | C91: South Asia | D91: Lower middle income | E91: IBRD
A92: Indonesia | B92: IDN | C92: East Asia & Pacific | D92: Upper middle income | E92: IBRD
A93: Iran, Islamic Rep. | B93: IRN | C93: Middle East, North Africa, Afghanistan & Pakistan | D93: Upper middle income | E93: IBRD
A94: Iraq | B94: IRQ | C94: Middle East, North Africa, Afghanistan & Pakistan | D94: Upper middle income | E94: IBRD
A95: Ireland | B95: IRL | C95: Europe & Central Asia | D95: High income
A96: Isle of Man | B96: IMN | C96: Europe & Central Asia | D96: High income
A97: Israel | B97: ISR | C97: Middle East, North Africa, Afghanistan & Pakistan | D97: High income
A98: Italy | B98: ITA | C98: Europe & Central Asia | D98: High income
A99: Jamaica | B99: JAM | C99: Latin America & Caribbean | D99: Upper middle income | E99: IBRD
A100: Japan | B100: JPN | C100: East Asia & Pacific | D100: High income
...
